Workbook

Sheet Capabilities

Sheet Case Install
A1: Application/Component Name | B1: E2E Featrure # (Test Execution) | C1: Domain Feature # | D1: State | E1: Product | F1: Test Case Status | G1: Owner | H1: S.NO# / TC# | I1: Journey | J1: User Experience | K1: Description/Expected Results | L1: Actual Results | M1: Prod Need by Date | N1: Pass/Fail | O1: Executed By | P1: Environment | Q1: Data | R1: Rally Defect# | S1: Tester Comments
A2: Member Group and Member Enrollment-SAMX Fully Insured, Level Funded/Cirrus | I2: Integrated Open Enrollment Experience- Working together to attract membership and set Plan expectations. Members must be active during enrollment select PCP or a PCP will be assigned by UHC | J2: As a Broker I should be successfully able to generate a Quote and Proposal for my Employer Group and be able to enroll member groups and members into Cirrus | N2: Pass
H3: TC1 | I3: Member Group and Member Enrollment-OBM/Cirrus (Level Funded) | J3: OBM Member Group | K3: Create group through automation tool using Link Jenkins | L3: Same as expected | N3: Pass
H4: TC2 | K4: Update customer profile field based on CA state | L4: Same as expected | N4: Pass
H5: TC3 | K5: Verify group is install successfully with HMO Products (HMO-Migrated from Nice) SIGNATUREVALUE Product | N5: Pass
H6: TC4 | K6: Verify group is install successfully with HMO Products (HMO-Migrated from Nice) cover all SIGNATUREVALUE_ALLIANCE product | N6: Pass
H7: TC5 | K7: Verify group is install successfully with HMO Products (HMO-Migrated from Nice) cover all SIGNATUREVALUE_HARMONY product | N7: Pass
H8: TC6 | K8: Verify group is install successfully with HMO Products (HMO-Migrated from Nice) cover all SIGNATUREVALUE_ADVANTAGE products | N8: Pass
H9: TC7 | K9: Verify group is install successfully with HMO products+ PPO (Dual Options) | N9: Pass
H10: TC8 | K10: Verify group is install successfully with HMO Products +Dental+Vision | N10: Pass
H11: TC9 | K11: Verify group is install successfully with only HMO products+ PPO (Dual Options)+Dental+Vision | N11: Pass
H12: TC12 | K12: Update health products field based on your state (Plan name, BBOI, Network, Medical plan code, RX plan code) | L12: Same as expected | N12: Pass
H13: TC13 | K13: Validate and Publish the group | L13: Same as expected | N13: Pass
H14: TC14 | J14: Cirrus Validation - Member Group | K14: Verify Cirrus for Member Group and Member load from OBM | L14: Same as expected | N14: Pass
H15: TC15 | K15: Verfiy all members/ MG loaded successfully in Cirrus | L15: Same as expected | N15: Pass
H16: TC16 | K16: Verfiy an error queue for any installation errors. | L16: Same as expected | N16: Pass
H17: TC17 | K17: Verify all demographic details loaded successfully in Cirrus for Member Group | L17: Same as expected | N17: Pass
H18: TC18 | K18: Verify Bill group details are loaded successfully in Cirrus | L18: Same as expected | N18: Pass
H19: TC19 | K19: Verify Member Group Contract Plan Option Plan Code" Hyperlink on the Plan Option UI | N19: Pass
H20: TC20 | K20: Verify Bill rates are loaded successfully in Cirrus | L20: Same as expected | N20: Pass
H21: TC22 | K21: Verify Plan selected is loaded successfully in Cirrus | L21: Same as expected | N21: Pass
H22: TC23 | K22: Verify for level funded if carrier/legal entity on the SL policy is assigned correctly (Click here for LE) | N22: Pass
H23: TC24 | K23: Verify MG contract option has ID card hold in place | L23: Same as expected | N23: Pass
H24: TC25 | J24: OBM Member | K24: Update mandatory field in Excel sheet (Employee SSN, Relationship Code, Medical Benefit Status Code, Last Name, First Name, SEX, Date of Birth, Address Type, Street Address, City, State, ZIP, Phone Type, Home_Phone, Hire Date, Employment Status Code, Employment Status Effective Date, Medical Coverage, Medical Benefit Bundle Option ID, Medical Bill Group ID, Benefit Status Code and Member Group ID) | L24: Same as expected | N24: Pass
H25: TC26 | K25: Publish the excel sheet in USP member in OBM | L25: Same as expected | N25: Pass
H26: TC27 | J26: CIP | K26: Validate member enrollment file can be submitted with NICE membership via (CIP > CMT > Cirrus) | N26: Not Applicable
H27: TC28 | J27: Cirrus Validation - Member Group | K27: Verify Cirrus for Member Group and Member load from OBM | L27: Same as expected | N27: Pass
H28: TC29 | K28: Verfiy all members/ MG loaded successfully in Cirrus | L28: Same as expected | N28: Pass
H29: TC30 | K29: Verfiy an error queue for any installation errors. | L29: Same as expected | N29: Pass
H30: TC31 | K30: Verify all demographic details loaded successfully in Cirrus for Member Group | L30: Same as expected | N30: Pass
H31: TC32 | K31: Verify Bill group details are loaded successfully in Cirrus | L31: Same as expected | N31: Pass
H32: TC33 | K32: Verify Bill rates are loaded successfully in Cirrus | L32: Same as expected | N32: Pass
H33: TC34 | K33: Verify we are able to see New Book of Business for NICE - UHC West | L33: Same as expected | N33: Pass
H34: TC35 | K34: Verify legal entity is correctly setup - UHC of California | L34: Same as expected | N34: Pass
H35: TC36 | K35: Verify Plan selected is loaded successfully in Cirrus | L35: Same as expected | N35: Pass
H36: TC37 | K36: Verify MG contract option has ID card hold in place | L36: Same as expected | N36: Pass
H37: TC38 | J37: Cirrus Validation - Membership | K37: Verify all demographic details loaded successfully in Cirrus for all members | L37: Same as expected | N37: Pass
H38: TC39 | K38: Verify contact details loaded successfully in Cirrus for all members | L38: Same as expected | N38: Pass
H39: TC40 | K39: Verify member billing information loaded successfully in subsaffiliation page in Cirrus for all members | L39: Same as expected | N39: Pass
H40: TC41 | K40: Verify member CLC is calculated correctly | L40: Same as expected | N40: Pass
H41: TC42 | K41: Verify we are able to see Benefit Plan Status (Active, COBRA, Surviving) | L41: Same as expected | N41: Pass
H42: TC43 | K42: Verify Member Employment Status (Active, Retired, Full Time, Part Time) | L42: Same as expected | N42: Pass
H43: TC44 | K43: Validate Coordination of Benefits for members | L43: Same as expected | N43: Pass
H44: TC45 | K44: Verify all members benefit data loaded correctly in Benefit Plan page | L44: Same as expected | N44: Pass
H45: TC46 | K45: Verify member can be enrolled into COBRA | L45: Same as expected | N45: Pass
H46: TC47 | I46: Member group Install - DSS (for manual installation) | K46: Verify Cirrus for Member Group and Member load through DSS | L46: Same as expected | N46: Pass
H47: TC48 | K47: Verify group is install successfully with HMO Products (HMO-Migrated from Nice) SIGNATUREVALUE Product | L47: Same as expected | N47: Pass
H48: TC49 | K48: Verify group is install successfully with HMO Products (HMO-Migrated from Nice) cover all SIGNATUREVALUE_ALLIANCE product | L48: Same as expected | N48: Pass
H49: TC50 | K49: Verify group is install successfully with HMO Products (HMO-Migrated from Nice) cover all SIGNATUREVALUE_HARMONY product | L49: Same as expected | N49: Pass
H50: TC51 | K50: Verify group is install successfully with HMO Products (HMO-Migrated from Nice) cover all SIGNATUREVALUE_ADVANTAGE products | L50: Same as expected | N50: Pass
H51: TC52 | K51: Verify group is install successfully with HMO products+ PPO (Dual Options) | L51: Same as expected | N51: Pass
H52: TC53 | J52: Cirrus Validation - Member Group | K52: Verify benefit bundle match for Level 2 product is applicable to Key Accounts in different situs states (ex: Louisiana & Florida) | L52: Same as expected | N52: Pass
H53: TC54 | K53: Verfiy all members/ MG loaded successfully in Cirrus | L53: Same as expected | N53: Pass
H54: TC55 | K54: Verfiy an error queue for any installation errors. | L54: Same as expected | N54: Pass
H55: TC56 | K55: Verify all demographic details loaded successfully in Cirrus for Member Group | L55: Same as expected | N55: Pass
H56: TC57 | K56: Verify Bill group details are loaded successfully in Cirrus | L56: Same as expected | N56: Pass
H57: TC58 | K57: Verify for level funded if carrier/legal entity on the SL policy is assigned correctly (Click here for LE) | L57: Same as expected | N57: Pass
H58: TC59 | K58: Verify Bill rates are loaded successfully in Cirrus | L58: Same as expected | N58: Pass
H59: TC60 | K59: Verify Plan selected is loaded successfully in Cirrus | L59: Same as expected | N59: Pass
H60: TC61 | K60: Verify MG contract option has ID card hold in place | L60: Same as expected | N60: Pass
H61: TC62 | J61: Cirrus Validation - Membership | K61: Verify members can be enrolled in groups by loading them directly into Cirrus via Proprietary X tool, EDI or JSON | L61: Same as expected | N61: Pass
H62: TC63 | K62: Verify all demographic details loaded successfully in Cirrus for all members | L62: Same as expected | N62: Pass
H63: TC64 | K63: Verify contact details loaded successfully in Cirrus for all members | L63: Same as expected | N63: Pass
H64: TC65 | K64: Verify member billing information loaded successfully in subsaffiliation page in Cirrus for all members | L64: Same as expected | N64: Pass
H65: TC66 | K65: Verify member CLC is calculated correctly | L65: Same as expected | N65: Pass
H66: TC67 | K66: Verify all members benefit data loaded correctly in Benefit Plan page | L66: Same as expected | N66: Pass

Sheet Fulfillment
A1: Application/Component Name | B1: E2E Featrure # (Test Execution) | C1: Domain Feature # | D1: State | E1: Product | F1: Test Case Status | G1: Owner | H1: S.NO# / TC# | I1: Journey | J1: User Experience | K1: Description/Expected Results | L1: Actual Results | M1: Prod Need by Date | N1: Pass/Fail | O1: Executed By | P1: Environment | Q1: Data | R1: Rally Defect# | S1: Tester Comments
H2: TC1 | I2: Id Card Trigger Member-> Benefit Plan-> Id Card. | J2: Cirrus UI id card trigger and validation | K2: Verify if you are able to trigger the ID Cards. | L2: Same as expected | N2: Pass
H3: TC2 | K3: Verify after requesting the Id Card member's fulfulment request status is successful or not in Cirrus fulfillment request search option. Member-> More Member-> Fulfilment request scearch. | L3: Same as expected | N3: Pass
A4: Fulfillment | H4: TC3 | I4: Integrated Open Enrollment Experience Working together to attract membership and set Plan expectations. Coordinated approach to onboarding. Members must be active during enrollment select PCP or a PCP will be assigned by UHC | J4: As a member I am able to receive my health insurance ID card and other fulfillment material | K4: Verify ID Cards are triggered from Cirrus as per the scheduled date | L4: Same as expected | N4: Pass
H5: TC4 | K5: Verify ID cards PDFs are generated in Fiserv as expected with requirements. | L5: Same as expected | N5: Pass
H6: TC5 | K6: Verify PCP name is printed on ID card for individual provider <as applicable> | L6: Same as expected | N6: Pass
H7: TC6 | K7: Verify Provider group name is printed on ID card when PCP is a medical group. <as applicable> | L7: Same as expected | N7: Pass
H8: TC7 | K8: Verify ACO name is printed on ID card when PCP is from the ACO roster <as applicable> | L8: Same as expected | N8: Pass
H9: TC8 | K9: Verify product name, legal entity and logo are displayed on the ID card as expected | L9: Same as expected | N9: Pass
H10: TC9 | K10: Verify Benefits - Benefit Plan - Accumulators - Benefit Deductibles - Deductible Periods are displayed on the ID card as expected | L10: Same as expected | N10: Pass
H11: TC10 | K11: Verify member's first name, middle name, last name and suffix are displayed on Id Card. | L11: Same as expected | N11: Pass
H12: TC11 | K12: Verify member's external id and benefit plan group id matches with Cirrus and displayed. | L12: Same as expected | N12: Pass
H13: TC12 | K13: Verify Member's benefit plan name is printed in the Id Card as expected | L13: Same as expected | N13: Pass
H14: TC13 | K14: Verify rx effective date and member's benefit plan payer id is display. | L14: Same as expected | N14: Pass
H15: TC14 | K15: Verify member's fulfilment product name with network scheduled display | L15: Same as expected | N15: Pass
H16: TC15 | K16: Verify Copays printed on ID card are correct per the benefit plan | L16: Same as expected | N16: Pass
... H26: TC25 | K26: Validate that Business approval is obtained for ID CARD | L26: Same as expected | N26: Pass
H27: TC26 | I27: Plan Documents | K27: Verify once group is installed sucessfully, events should be created automatlically | L27: Same as expected | N27: Pass
H28: TC27 | K28: verify if the events are triggerd sucussfully and its in Complete staus in Cirrus | L28: Same as expected | N28: Pass
H29: TC28 | K29: Verify events are in Archive status in DB once COM360 is done processing | L29: Same as expected | N29: Pass
H30: TC29 | K30: Verify other fulfillment materials (COC, SBC) <as applicable> | L30: Same as expected | N30: Pass
H31: TC30 | K31: Verify other NODA transaction is completed successfully and content is correct <as needed and applicable> | L31: Same as expected | N31: Not Applicable
H32: TC31 | K32: Verify benefit language <as applicable> in B360 (for fully insured) | L32: Same as expected | N32: Pass
H33: TC32 | K33: Verify benefit language in B360 vs benefit language in Cirrus | L33: Same as expected | N33: Pass
H34: TC33 | J34: BEACH | K34: Verify benefit language in BEACH application | L34: Same as expected | N34: Pass
H35: TC34 | K35: Verify Coverage Inforamtion in BEACH | L35: Same as expected | N35: Pass
H36: TC35 | K36: Verify we are able to pull plan documents from Coerage or Costs Tab. | L36: Same as expected | N36: Pass

Sheet Downstream Extract
A1: Application/Component Name | B1: E2E Featrure # (Test Execution) | C1: Domain Feature # | D1: State | E1: Product | F1: Test Case Status | G1: Owner | H1: S.NO# / TC# | I1: Journey | J1: User Experience | K1: Description/Expected Results | L1: Actual Results | M1: Prod Need by Date | N1: Pass/Fail | O1: Executed By | P1: Environment | Q1: Data | R1: Rally Defect# | S1: Tester Comments
I2: Non-Finance Downstream Extracts/Streaming
H3: TC68 | J3: Optum Bank | K3: Verfiy HSA vendor ID is populated on mem group contract plan option screen | L3: Same as expected | N3: Pass
H4: TC69 | K4: Verify if you are able to add Signature date on affiliation screen of members(New Business) | L4: Same as expected | N4: Pass
H5: TC70 | K5: Verify if Banking Extract is getting generated | L5: Same as expected | N5: Pass
H6: TC71 | K6: Verify If Member group & Member Data is present in extract | L6: Same as expected | N6: Pass
H7: TC72 | K7: Verify if B2B is able to consume membership file and is able to translate the file | L7: Same as expected | N7: Pass
H8: TC73 | K8: Verfiy OptumBank is able to consume Member group and member data via the extract for Member group and members enrolled in HSA plans | L8: Same as expected | N8: Pass
H9: TC74 | K9: Examine the load report sent by Optum Bank to verify that all the memebrs and member groups have been corretly loaded. | L9: Same as expected | N9: Pass
H10: TC75 | J10: Optum Rx | K10: Verfiy OptumRX is able to consume Member group and membership data via Nimbus stream | L10: Same as expected | N10: Pass
H11: TC76 | K11: Verify if the eligebility information effective date is same as member group contract effective date in Optum Rx UI. | L11: Same as expected | N11: Pass
H12: TC77 | K12: Verify if Member group data is correctly available in OptumRx Portal(Demographics/DOB/MG name etc) | L12: Same as expected | N12: Pass
H13: TC78 | K13: Verify if Client code is available in optum RX portal | L13: Same as expected | N13: Pass
H14: TC79 | K14: Verify if all members are loaded in Optum Rx UI | L14: Same as expected | N14: Pass
H15: TC80 | K15: Verify if demegraphics details are present in the Optum Rx UI | L15: Same as expected | N15: Pass
H16: TC81 | J16: Dental | K16: Verfiy Dental is able to consume Member group and Membership data via Nimbus stream | L16: Same as expected | N16: Pass
H17: TC82 | J17: Vision | K17: Verfiy Vision is able to consume Member group and Membership data via Nimbus stream | L17: Same as expected | N17: Pass
H18: TC83 | J18: PHAccent | K18: Verify if Extract is getting generated for the MG which has benefit plan with Plan Category 1 as attribute | L18: Same as expected | N18: Pass
H19: TC84 | K19: Verify if MG & member available in extract | L19: Same as expected | N19: Pass
H20: TC85 | K20: Verify if Bundle option is available in benefit plan summary extract | L20: Same as expected | N20: Pass
H21: TC86 | K21: Verfiy PH Accent is able to consume Member group and Membership data via extract | L21: Same as expected | N21: Pass
H22: TC87 | K22: Examine the loadreport sent by PHAccent to verify that all the memebrs and member groups have been corretly loaded. | L22: Same as expected | N22: Pass
H23: TC88 | J23: BOSS | K23: Verfiy BOSS is able to consume Member group data from Data Lake via Digicom | L23: Same as expected | N23: Pass
H24: TC89 | K24: Examine the loadreport sent by BOSS to verify that all the memebrs and member groups have been corretly loaded. | L24: Same as expected | N24: Pass
H25: TC90 | J25: BEACH | K25: Verify benefit language in BEACH application | L25: Same as expected | N25: Pass
H26: TC91 | K26: Verify Coverage Inforamtion in BEACH | L26: Same as expected | N26: Pass
H27: TC92 | K27: Verify we are able to pull plan documents from Coerage or Costs Tab. | L27: Same as expected | N27: Pass

Sheet Bill&Comm
A1: Application/Component Name | B1: E2E Featrure # (Test Execution) | C1: Domain Feature # | D1: State | E1: Product | F1: Test Case Status | G1: Owner | H1: S.NO# / TC# | I1: Journey | J1: User Experience | K1: Description/Expected Results | L1: Actual Results | M1: Prod Need by Date | N1: Pass/Fail | O1: Executed By | P1: Environment | Q1: Data | R1: Rally Defect# | S1: Tester Comments
A2: Billing | H2: TC1 | J2: As an Employer group I should be able to View my Bill | K2: Verify if membership eligiblity is streamed through Nimbus to BRMS | L2: Same as expected | N2: Pass
H3: TC2 | K3: Verfiy FTS is able to consume PCMT | L3: Same as expected | N3: Pass
H4: TC3 | K4: Verify if we can see Member groups in Invoices | L4: Same as expected | N4: Pass
H5: TC5 | K5: Verify if can see Members in Invoices | L5: Same as expected | N5: Pass
H6: TC6 | K6: Verify if based on the billing schedule on our group Billing calculation is correct. | L6: Same as expected | N6: Pass
H7: TC7 | K7: Verify if we can see our invoices in B&E portal | L7: Same as expected | N7: Pass
A8: Commission | H8: TC8 | J8: As a Broker I should be able to View my Commission | K8: Verfiy BASICS able to consume data sent by BRMS & Cirrus | L8: Same as expected | N8: Pass
H9: TC9 | K9: Verify if we can see all our Member groups in commission statements. | L9: Same as expected | N9: Pass
H10: TC10 | K10: Verify if our Producer / sales agent name is matching with Commission statements. | L10: Same as expected | N10: Pass
H11: TC11 | K11: Verify if compensation type is service Fee or commission for Service fee we should see PEPM in statement as rate should be fixed based on the no. of employes for Commission there should be some percent of premium paid in to no. of employes in the group. | L11: Same as expected | N11: Pass
H12: TC12 | K12: Verify if we can see Commissions for all products which we have in our groups. | L12: Same as expected | N12: Pass

Sheet Maint
A1: Application/Component Name | B1: E2E Featrure # (Test Execution) | C1: Domain Feature # | D1: State | E1: Product | F1: Test Case Status | G1: Owner | H1: S.NO# / TC# | I1: Journey | J1: User Experience | K1: Description/Expected Results | L1: Actual Results | M1: Prod Need by Date | N1: Pass/Fail | O1: Executed By | P1: Environment | Q1: Data | R1: Rally Defect# | S1: Tester Comments
A2: Member Group and Member Maintenance | F2: Designed | I2: Integrated Open Enrollment Experience- Working together to attract membership and set Plan expectations. | J2: I should be successfully able to update member group and members in Cirrus | N2: Pass
F3: Designed | H3: TC1 | J3: Cirrus Validation - Member Group | K3: Verify if we are able to Term a Member Group | L3: Same as expected | N3: Pass
F4: Designed | H4: TC2 | K4: Verify if we are able to Cancel a Member Group | L4: Same as expected | N4: Pass
F5: Designed | H5: TC3 | K5: Verify if we are able to Reinstate a Member Group | L5: Same as expected | N5: Pass
F6: Designed | H6: TC4 | K6: Verify if we are able to update Member Group- Demographics, plan information | L6: Same as expected | N6: Pass
F7: Designed | H7: TC6 | K7: Verify if we are able to retro term a Member Group | L7: Same as expected | N7: Pass | S7: MG: 3017649
F8: Designed | H8: TC7 | K8: Verify if we are able to retro reinstate a Member Group | L8: Same as expected | N8: Pass | R8: DE1262623 | S8: MG: 3017649 / Failing on Member SCID: 32334628900 / Member Group:5431025
F9: Designed | H9: TC8 | K9: Verify if we are able to retro change a plan to Member Group | L9: Same as expected | N9: Pass
F10: Designed | H10: TC9 | J10: Cirrus Validation - Membership | K10: Verify if we are able to add a dependent | L10: Same as expected | N10: Pass
F11: Designed | H11: TC10 | K11: Verify if we are able to term a Member | L11: Same as expected | N11: Pass
F12: Designed | H12: TC11 | K12: Verify if we are able to reinstate a Member | L12: Same as expected | N12: Pass
F13: Designed | H13: TC12 | K13: Verify if we are able to move Member to COBRA | L13: Same as expected | N13: Pass | R13: DE1262631 | S13: Closed/Completed - Incorrect Termination Status in BnE
F14: Designed | H14: TC13 | K14: Verify if we are able to update Member demographics | L14: Same as expected | N14: Pass
F15: Designed | H15: TC14 | K15: Verify if we are able to retro add Member with dependent | L15: Same as expected | N15: Pass
F16: Designed | H16: TC15 | K16: Verify if we are able to retro term a Member | L16: Same as expected | N16: Pass
F17: Designed | H17: TC16 | K17: Verify if we are able to retro reinstate a Member | L17: Same as expected | N17: Pass
F18: Designed | H18: TC17 | K18: Verify if we are able to retro change a plan to Member | L18: Same as expected | N18: Pass
A19: Broker & Employer Portal | H19: TC18 | I19: Integrated Open Enrollment Experience- Working together to attract membership and set Plan expectations. Members must be active during enrollment select PCP or a PCP will be assigned by UHC | J19: As an Employer group I should be able to add, change and update my employee information -- B&E | K19: Verify Employer group is able to login to B&E Portal/ UHCeServices.com | L19: Same as expected | N19: Pass
H20: TC19 | K20: Verify Employer group should be able to enroll members | L20: Same as expected | N20: Pass
H21: TC20 | K21: Verify as a Employer group I should be able to see my group's information-Demographics and plans | L21: Same as expected | N21: Pass
H22: TC21 | K22: Verify as a Employer group I should be able to see my billing information | L22: Same as expected | N22: Pass
H23: TC22 | K23: Verify as a Broker I should be able to see my commission statement | L23: Same as expected | N23: Pass | S23: BRMS In Progress
H24: TC23 | K24: Verify as a Employer group I should be able to see my COC | L24: Same as expected | N24: Pass
H25: TC24 | K25: Verify as a Employer group I should be able to see my subscriber and member list | L25: Same as expected | N25: Pass
H26: TC25 | K26: Verify as a Employer group I should be able to see my employee information | L26: Same as expected | N26: Pass
H27: TC26 | K27: Verify we are able to search PCP for Products requring PCP | L27: Same as expected | N27: Pass
H28: TC27 | K28: Verify if we are able to add a dependent | L28: Same as expected | N28: Pass
H29: TC28 | K29: Verify if we are able to term a Member | L29: Same as expected | N29: Pass
H30: TC29 | K30: Verify if we are able to add a Member with COBRA | L30: Same as expected | N30: Pass
H31: TC30 | K31: Verify if we are able to update Member demographics | L31: Same as expected | N31: Pass
H32: TC31 | K32: Verify if we are able to Add Member PCP | L32: Same as expected | N32: Pass
H33: TC30 | K33: Verify if the Ability for NICE Groups to view, Plan Rates , view Benefits & Plan Information | L33: Same as expected | N33: Pass
K34: Verify if the Ability for NICE Groups to EDI reports, MLR Reports, CER reports, Banking Reports etc Enhance the group search functions to display old and new contract effective dates | L34: Same as expected | N34: Not Applicable
H35: TC34 | K35: PCP Validation : Existing Patient Indicator, PCP Cirrus rules for auto assigning ,PCP, billing Group Plan Info on view Group Page, Provider Error messaging., Disable Add Additional provider button | L35: Same as expected | N35: Pass
H36: TC35 | K36: Verify we are able to view member ID cards | L36: Same as expected | N36: Pass | S36: Config is not ready for ID Card
H37: TC36 | K37: Validate in Reason for Enrollment section there will be 3 Different Cobra - Cobra18, cobra29, cobra36 | L37: Same as expected | N37: Not Applicable | S37: Per Kim, As these are not requirements for the NICE Migration, we are not asking for user testing for them.
H38: TC37 | K38: Validate in gender enrollment demographics has gender option Unknown not Non-binary | L38: Same as expected | N38: Pass
H39: TC38 | K39: Validate in Qualifying Event and Requested Effective Date user can enroll 90 days past, out of this range they will see an error and cannot proceed with enrollment. | L39: Same as expected | N39: Not Applicable | S39: Not applicable for 90 days past.
H40: TC38 | K40: Validate in Qualifying Event and Requested Effective Date user can enroll 60 days in future, out of this range they will see an error and cannot proceed with enrollment. | L40: Same as expected | N40: Pass | S40: Not applicable for 90 days past.
H41: TC39 | K41: Validate in Subscriber Information Enrollment Demographics should have Subscriber Type (Employee/Retiree) ,Marital Status (Married/Single). | L41: Same as expected | N41: Pass
H42: TC40 | K42: Validate In Contact Information Enrollment Demographics should have COB field (Coordination of Benefits Yes/No) | L42: Same as expected | N42: Pass
H43: TC41 | K43: NICE does not have the option Select Reason SSN not provided, and SSN dup check validation exists for NICE, will have to find out if Cirrus adopt this SSN validation? | L43: Same as expected | N43: Not Applicable
H44: TC42 | K44: Validate for Enrollment Dependent newly added field are available | L44: Same as expected | N44: Pass

Sheet DE
A1: Application/Component Name | B1: E2E Featrure # (Test Execution) | C1: Domain Feature # | D1: State | E1: Product | F1: Test Case Status | G1: Owner | H1: S.NO# / TC# | I1: Journey | J1: User Experience | K1: Description/Expected Results | L1: Actual Results | M1: Prod Need by Date | N1: Pass/Fail | O1: Executed By | P1: Environment | Q1: Data | R1: Rally Defect# | S1: Tester Comments
A2: ACET | C2: NICE | D2: CA | H2: TC1 | J2: ACET Member Flow (DashBoard) | K2: As a agent we are able to view member details in ACET | L2: Same as expected | N2: Pass
C3: NICE | D3: CA | H3: TC2 | K3: As a agent we are able to view - Benefit Information in ACET | N3: Pass
C4: NICE | D4: CA | H4: TC4 | K4: As a agent we are able to create and send letters specific to CA HMO (NICE) business to Member | L4: Same as expected | N4: Not Applicable
C5: NICE | D5: CA | H5: TC5 | K5: As a agent we are able to create a case and Rout toplan benefits | L5: Same as expected | N5: Pass
C6: NICE | D6: CA | H6: TC6 | K6: As a agent we are able to view the member's claim and As a member payment details (Member resp / Prov resp / Total Billed etc) | L6: Same as expected | N6: Pass
C7: NICE | D7: CA | H7: TC7 | K7: As a agent we are able to Able to launch AVA in order to research the member's plan benefits | L7: Same as expected | N7: Pass
C8: NICE | D8: CA | H8: TC8 | K8: As an agent, I can view a member's medical coverage effective and end dates based on the medical plan they are enrolled in | L8: Same as expected | N8: Pass
C9: NICE | D9: CA | H9: TC9 | K9: As an agent, I can verify a member's medical coverage details and verify the data matches in cirrus | L9: Same as expected | N9: Pass
C10: NICE | D10: CA | H10: TC10 | K10: As an agent, I can view the carrier of the member's plans in a yellow banner located on the top of the member details page | L10: Same as expected | N10: Pass
C11: NICE | D11: CA | H11: TC11 | K11: As an agent, If a member is enrolled in Speciality Plans, I can validate speciality coverage in a separate tab on the members detail page (Ex: Dental/Vision) | L11: Same as expected | N11: Not Applicable
C12: NICE | D12: CA | H12: TC12 | K12: As an agent, I can view ancillary product offerings available to the member I am servicing (Ex Service Plans: Advocate4me, HealthiestYou, RallyHealth Wellness Program) (Ex: Utilization Plans: Behaviroal Health Sanvello etc.) | L12: Same as expected | N12: Pass
C13: NICE | D13: CA | H13: TC13 | K13: As an agent, I have the ability to view a PCP assigned to the member and update upon request | L13: Same as expected | N13: Pass
C14: NICE | D14: CA | H14: TC14 | K14: As an agent, I have the ability to view a member's spending account including total claims via INN / OON represented by a graph | L14: Same as expected | N14: Pass
C15: NICE | D15: CA | H15: TC15 | K15: As an agent, I have the ability to search/view documents issued to the member (SBC, COC, EOB etc.) | L15: Same as expected | N15: Pass
C16: NICE | D16: CA | H16: TC16 | J16: Communications | K16: As an agent, if a member has health coverage with another carrier then it should be displayed against member name under commercial/govt | L16: Same as expected | N16: Pass
C17: NICE | D17: CA | H17: TC17 | J17: Coordination of Benefits | K17: As an agent, I am able to view a member's current employer and the contract option of that group including coverage effective/end date | L17: Same as expected | N17: Pass
C18: NICE | D18: CA | H18: TC18 | J18: Group Eligibility | K18: As an agent, I have the ability to access details for a member's plan (Medical Plan ID, Effective date, End Date, etc.) | L18: Same as expected | N18: Pass
C19: NICE | D19: CA | H19: TC19 | J19: Plan Benefits | K19: As an agent, I have the ability to view the plan attributes offered in the member's plan (ex: UHPD) | L19: Same as expected | N19: Pass
C20: NICE | D20: CA | H20: TC20 | K20: As an agent, when selecting on the member's plan, I will be able to view the member's accumulators (Ded / OOP for Ind & family) offered in their plan | L20: Same as expected | N20: Pass
C21: NICE | D21: CA | H21: TC21 | K21: As an agent, when accessing a member's benefit plan details page, I am able to select a benefit code for that member and view language for Tier 1, In-Network, Out-Of-Network services | L21: Same as expected | N21: Pass
C22: NICE | D22: CA | H22: TC22 | K22: As an agent, when servicing a member on NICE plan I am able to view a member's benefits (Tier 1, In-Network, Out-of-Network)through an integrated experience of B360. | L22: Same as expected | N22: Pass
C23: NICE | D23: CA | H23: TC23 | J23: Provider Lookup | K23: As an agent, I have the ability to perform a provider lookup with the member's eligibility in focus. I can apply an filter based on the product design to search for a provider covered in the member's plan (Ex: Tiered provider, OXPLN, DDP etc.) | L23: Same as expected | N23: Pass
C24: NICE | D24: CA | H24: TC24 | J24: View Claims | K24: As an agent, I have the ability to view the member's claim and validate payment details (Member resp / Prov resp / Total Billed etc) | L24: Same as expected | N24: Pass
C25: NICE | D25: CA | H25: TC25 | J25: ID card request | K25: As an agent, I have the ability to submit an ID card request for member | L25: Same as expected | N25: Pass
C26: NICE | D26: CA | H26: TC26 | J26: View Authorization | K26: As an agent, I have the ability to viewe a prior authorization submitted for the member I am servicing | L26: Same as expected | N26: Pass
C27: NICE | D27: CA | H27: TC27 | K27: As an agent, I have the ability to create an authorization for the member I am servicing when selecting the URL that will perform a SSO to ICUE | L27: Same as expected | N27: Deferred
C28: NICE | D28: CA | H28: TC28 | J28: View PCP referral | K28: As an agent servicing a member on a gated plan, I should be able to view any referral submitted for that member. | L28: Same as expected | N28: Pass
C29: NICE | D29: CA | H29: TC31 | J29: View member listing | K29: As an agent, I am able to view members enrolled in a group in cirrus should also be displayed in ACET correctly | L29: Same as expected | N29: Pass
A30: ACET BEO (Group Eligibility) | C30: NICE | D30: CA | H30: TC32 | J30: ACET BEO (Group Eligibility) | K30: As a agent, we are able to view Group Contract option version and cross As a member in ACET | L30: Same as expected | N30: Pass
C31: NICE | D31: CA | H31: TC33 | J31: Group Plan | K31: As a agent, plans offered to a group including eff/exp dates from cirrus in ACET | L31: Same as expected | N31: Pass
C32: NICE | D32: CA | H32: TC34 | J32: View member listing | K32: As a agent, members enrolled in a group in cirrus should also be displayed in ACET correctly | L32: Same as expected | N32: Pass
C33: NICE | D33: CA | H33: TC35 | K33: As a agent,, I am able to view all claims and filter by Date of Service as part of my search | L33: Same as expected | N33: Pass
A34: ACET - Spire | C34: NICE | D34: CA | H34: TC37 | I34: Dashboard (Provider Details) | J34: Search providers | K34: As an agent, I have the ability to search providers with the help of filters and verify details of a particular provider in cirrus. | L34: Same as expected | N34: Pass | O34: Jawahar
C35: NICE | D35: CA | H35: TC39 | J35: Active Affiliations | K35: As an agent, I have the ability to view Provider speciality, affiliation and effective date from Cirrus (Speciality is under Taxonomy tab in cirrus) | L35: Same as expected | N35: Pass | O35: Jawahar
C36: NICE | D36: CA | H36: TC40 | J36: Contracts | K36: As an agent, I have the ability to view contract details for a provider (ex: Network id, pricing set) | L36: Same as expected | N36: Pass | O36: Jawahar
C37: NICE | D37: CA | H37: TC41 | I37: View Member Eligibility | J37: Member Snapshot | K37: As an agent , I have the ability to verify Household ,member Details, Policy Details, PCP History | L37: Same as expected | N37: Pass | O37: Jawahar
C38: NICE | D38: CA | H38: TC42 | I38: View Member Eligibility/View Claims | J38: Member Snapshot/Claim Detail | K38: As an agent , I have the ability to verify COB | L38: Same as expected | N38: Not Applicable | O38: Jawahar
C39: NICE | D39: CA | H39: TC43 | I39: Plan Benefits | J39: PA check (Provider and Member Information) | K39: As an agent , I have ability to check member and provider information . | L39: Same as expected | N39: Pass | O39: Jawahar
C40: NICE | D40: CA | H40: TC44 | J40: PA check (Create Auth) | K40: As an agent, I have the ability to Create Auth in Spire successfully | L40: Same as expected | N40: Not Applicable | O40: Jawahar
C41: NICE | D41: CA | H41: TC45 | J41: Auth Verification (Cirrus and icue) | K41: Verify if auth is reflecting in cirrus and ICUE | L41: Same as expected | N41: Pass | O41: Jawahar
C42: NICE | D42: CA | H42: TC46 | J42: Authorization Results | K42: As an agent, I have the ability to view the auth in Spire. | L42: Same as expected | N42: Deferred | O42: Jawahar | S42: Known Issue - Some time this is not visible due to Environment connectivity issue.
C43: NICE | D43: CA | H43: TC47 | J43: Authorization Status | K43: As an agent , I have the ability to verify auth if all required information is showing in auth. | L43: Same as expected | N43: Not Applicable | O43: Jawahar | S43: Known Issue - Some time this is not visible due to Environment connectivity issue.
C44: NICE | D44: CA | H44: TC48 | J44: Create Referral | K44: As an agent, I have the ability to Create Referral in spire | L44: Same as expected | N44: Not Applicable | O44: Jawahar
C45: NICE | D45: CA | H45: TC49 | J45: Referral Results | K45: As an agent, I am able to verify referral in spire | L45: Same as expected | N45: Pass | O45: Jawahar | S45: Known Issue - Some time this is not visible due to Environment connectivity issue.
C46: NICE | D46: CA | H46: TC50 | J46: Benefit Accumulations (Therapy & Non Therapy) | K46: As an agent , I have the ability to verify benefit accumulations (Therapy , Dental, vision, DME etc) | L46: Same as expected | N46: Not Applicable | O46: Jawahar
C47: NICE | D47: CA | H47: TC51 | J47: Benefit Details | K47: As an agent , I have the ability to verify benefit details (Benefit Language , INN/OON Coverage and Benefit Category/Description/Cost Share) | L47: Same as expected | N47: Pass | O47: Jawahar | S47: Known Issue - Benefit Language not Visible - Some time this is not visible due to Environment connectivity issue.
C48: NICE | D48: CA | H48: TC52 | J48: Financials | K48: As an agent , I have the ability to verify Verify members responsibility met ( Cost share INN , OON and Tier1) | L48: Same as expected | N48: Pass | O48: Jawahar
C49: NICE | D49: CA | H49: TC53 | I49: View Claims | J49: Claim Results | K49: As an agent , I have the ability to verify claim in spire | L49: Same as expected | N49: Deferred | O49: Jawahar | S49: Known Issue - Benefit Language not Visible - Some time this is not visible due to Environment connectivity issue.
C50: NICE | D50: CA | H50: TC54 | I50: View Appeals | J50: Appeal Results | K50: As an agent , I have the ability to verify appeals submitted. | L50: Same as expected | N50: Not Applicable | O50: Jawahar
C51: NICE | D51: CA | H51: TC55 | I51: View Payments(Member Snapshot/Provider Snapshot) | J51: Payment Results | K51: As an agent , I have the ability to verify payments for both member and provider topics. | L51: Same as expected | N51: Not Applicable | O51: Jawahar | S51: Known Issue - Claims in Alpha are always showing payment in waiting cycle. EOB PRA are never generared. So this is not possible in Alpha. EOB PRAs are generated in Master only and Spire is not have connectivity with Master.
C52: NICE | D52: CA | H52: TC56 | I52: Provider Lookup(Member Snapshot) | J52: Provider search | K52: As an agent , I have the ability to serach provider in spire | L52: Same as expected | N52: Pass | O52: Jawahar
C53: NICE | D53: CA | H53: TC57 | J53: Provider Results | K53: Verify if we are able to see providers results after search | L53: Same as expected | N53: Pass | O53: Jawahar
C54: NICE | D54: CA | H54: TC58 | I54: Provider Lookup(Provider Snapshot) | J54: Provider Details | K54: As an agent I have the ability to verify details of searched provider. | L54: Same as expected | N54: Pass | O54: Jawahar
A55: myUHC | C55: NICE | D55: CA | H55: TC59 | J55: Dashboard | K55: As a member we are able to Register a member in MyUHC | L55: Same as expected | N55: Pass
C56: NICE | D56: CA | H56: TC60 | K56: As a member on a gated plan, I have the ability to view any referrals submitted by my PCP | L56: Same as expected | N56: Not Applicable | O56: 112001614396
C57: NICE | D57: CA | H57: TC61 | K57: As a member on gated plan, I have the ability to view/add/update my PCP on the dashboard when logging into myuhc | L57: Same as expected | N57: Pass | O57: 112023698492
C58: NICE | D58: CA | H58: TC62 | K58: As a member, on a Non-Gated Plan, although I do not require PCP, I have the ability to add/update a PCP on the dashboard when logging into myuhc | L58: Same as expected | N58: Not Applicable
C59: NICE | D59: CA | H59: TC63 | K59: As a member, I have the ability to view my Individual/Family Deductible & OOP Max accumulators on the dashboard when logging into myuhc | L59: Same as expected | N59: Pass
C60: NICE | D60: CA | H60: TC64 | K60: As a member, I have the ability to view recently submitted claims on the dashboard when logging into myuhc | L60: Same as expected | N60: Pass
C61: NICE | D61: CA | H61: TC65 | K61: As a member, I have the ability to view my ID Card Modal window based on the coverage I am enrolled in (Medical, Dental, Vision) | L61: Same as expected | N61: Pass
C62: NICE | D62: CA | H62: TC66 | J62: "Find Price & Care" page | K62: As a member member can view/update pcp selection on find care page | L62: Same as expected | N62: Pass
C63: NICE | D63: CA | H63: TC67 | K63: As a member pcp assignment intial assigmnet and update can be done in MYUHC | L63: Same as expected | N63: Pass
C64: NICE | D64: CA | H64: TC68 | K64: As a member , I have the ability to view INN primary care providers offered in my plan by selecting Primary Care Physicians | L64: Same as expected | N64: Pass
C65: NICE | D65: CA | H65: TC69 | K65: As a member on a gated plan, any providers that require a referral will display an alerting me that a referral is required. | L65: Same as expected | N65: Pass
C66: NICE | D66: CA | H66: TC70 | K66: As a member, I have the ability to search by speciality type and view INN providers that cover services for the speciality selected (Example: Cardiologist) | L66: Same as expected | N66: Pass
C67: NICE | D67: CA | H67: TC71 | K67: As a member on plan w/ tiering applicable to (PCP/Specialists), providers designated as Tier 1 will display with an icon on the top of the page when accessing an authenticated experience of the directory | L67: Same as expected | N67: Not Applicable
C68: NICE | D68: CA | H68: TC72 | K68: As a member, I have the ability to select an INN provider and receive a cost estimate based on my benefits for the service covered. | L68: Same as expected | N68: Pass
C69: NICE | D69: CA | H69: TC73 | K69: As a member on a Level Funded plan, I have the ability to Access to Healthiest You when selecting Virtual Care | L69: Same as expected | N69: Not Applicable
C70: NICE | D70: CA | H70: TC74 | K70: As a member, I have the ability to view behavioral health providers in my network (Ex: Psychiatrist, Psychologists, etc.) | L70: Same as expected | N70: Pass
C71: NICE | D71: CA | H71: TC75 | K71: As a member with Vision coverage, I have the ability to find Optometrists covered in my network. | L71: Same as expected | N71: Pass
C72: NICE | D72: CA | H72: TC76 | K72: As a member with Dental Coverage, I have the ability to find any Dentistcovered in my network | L72: Same as expected | N72: Pass
C73: NICE | D73: CA | H73: TC77 | J73: Coverage & Benefits Page | K73: As a member Member can view benefits and coverage on coverage & benefits page | L73: Same as expected | N73: Pass
C74: NICE | D74: CA | H74: TC78 | K74: As a member, I am able to view view copays for major level services covered in my plan (PCP, Specialist, ER Visit, Virtual Visit, Urgent Care Visit) | L74: Same as expected | N74: Pass
C75: NICE | D75: CA | H75: TC79 | K75: As a member, when selecting view all medical coverage I can view INN & OON benefit language for benefits included in my plan (Ex:Diabetic Services, Behavioral Health Outpatient – Physicians Office, Hearing Aids) | L75: Same as expected | N75: Pass
C76: NICE | D76: CA | H76: TC80 | K76: As a member, I am able to view Mental Health Common Services offered in my plan | L76: Same as expected | N76: Pass
C77: NICE | D77: CA | H77: TC81 | K77: As a member on a UHC fully Insured plan, I am able to access Mental Health Hub to view information on mental health programs offered in my plan (Ex: AbleTo, Sanvello Program) | L77: Same as expected | N77: Pass
C78: NICE | D78: CA | H78: TC82 | K78: As a member, If I am enrolled in an ancillary dental plan, I am able to view my Plan Details & Common Dental Services covered in plan | L78: Same as expected | N78: Pass
C79: NICE | D79: CA | H79: TC83 | K79: As a member, if I am enrolled in a plan with embedded dental coverage, I will be able to view my plan details in the Dental Section | L79: Same as expected | N79: Pass
C80: NICE | D80: CA | H80: TC84 | K80: As a member, if I am enrolled in an ancillary vision plan, I have the ability to SSO to the vision portal to view plan details & services covered in my plan | L80: Same as expected | N80: Pass | O80: 112024398592
K81: Validate Edit PCP options and navigation. | N81: Pass
C82: NICE | D82: CA | H82: TC85 | K82: As a member, I have the ability to view documents and forms issued to me based on my coverage (Ex: IRS Tax forms, SBC, COC,SPD) for the plans that I am enrolled in | L82: Same as expected | N82: Pass
C83: NICE | D83: CA | H83: TC86 | J83: Claims & Account | K83: As a member member can submit a claim from claim&account page | L83: Same as expected | N83: Pass
C84: NICE | D84: CA | H84: TC87 | K84: As a member that the User Experience for "NI" BoB should mirror "UH" BoB member experience on USP | L84: Same as expected | N84: Pass
C85: NICE | D85: CA | H85: TC88 | K85: As a member that member can navigate to Claim & Account page and view payment details based on service provided (Ex: Total Amount, Plan Paid, Member Responsibility) | L85: Same as expected | N85: Pass
C86: NICE | D86: CA | H86: TC89 | K86: As a member that member can navigate to Claim & Account page and view explanation of benefits for the services incurred. | L86: Same as expected | N86: Not Applicable | O86: require EOB
C87: NICE | D87: CA | H87: TC90 | K87: As a member, I am able to view all claims and filter by Date of Service as part of my search | L87: Same as expected | N87: Pass
C88: NICE | D88: CA | H88: TC91 | K88: As a member, when selecting a Claim, I am able to view payment details based on service provided (Ex: Total Amount, Plan Paid, Member Responsibility) | L88: Same as expected | N88: Pass
C89: NICE | D89: CA | H89: TC92 | K89: As a member, I have the ability to view my prior authorizations submitted by my provider in the top right hand corner of the claims page | L89: Same as expected | N89: Pass
C90: NICE | D90: CA | H90: TC93 | K90: As a member, I have the ability to view my current Medical Account Summary (Deductible/OOP max) reflecting an accurate representation based on my claims. If I am on a plan with tiered accumulators, I will be able to select Tier 1 vs INN Accumulators in a dropdown to see my progress for each. | L90: Same as expected | N90: Pass
C91: NICE | D91: CA | H91: TC94 | K91: As a member, I have the ability to submit a claim reimbursment form | L91: Same as expected | N91: Pass
C92: NICE | D92: CA | H92: TC95 | K92: As a member, I have the ability to view claim documents based on my coverage | L92: Same as expected | N92: Pass
C93: NICE | D93: CA | H93: TC96 | K93: As a member, when selecting a claim, I have the ability to view my explanation of benefits for the services incurred. | L93: Same as expected | N93: Not Applicable | O93: require EOB

Sheet ClmsClin
A1: Application/Component Name | B1: E2E Featrure # (Test Execution) | C1: Domain Feature # | D1: State | E1: Product | F1: Test Case Status | G1: Owner | H1: S.NO# / TC# | I1: Capability | J1: User Experience | K1: Description/Expected Results | L1: Actual Results | M1: Prod Need by Date | N1: Pass/Fail | O1: Executed By | P1: Environment | Q1: Data | R1: Rally Defect# | S1: Tester Comments
A2: Claims (Adjudication & EOB/PRAs) | H2: TC1 | J2: As a provider and member, claims submitted by me should successfully get processed as per the applicable benefit coverage. | K2: Professional claims- Physcian Services- Verify claims are adjudicated successfully and submitted to OFIN for Payment. | L2: Same as expected | N2: Pass
H3: TC2 | K3: Professional claims (Staff Model PCP member)- Physcian Services for a provider in member's pcp org- Verify claims are adjudicated successfully and submitted to OFIN for Payment. | N3: Pass
H4: TC3 | K4: Institutional Inpatient claim- Verify claims are adjudicated successfully and submitted to OFIN for Payment | L4: Same as expected | N4: Pass
H5: TC4 | K5: Institutional Outpatient claim- Verify claims are adjudicated successfully and submitted to OFIN for Payment | L5: Same as expected | N5: Pass
H6: TC5 | K6: OON Claim-Verify claims are adjudicated successfully and submitted to OFIN for Payment | L6: Same as expected | N6: Pass
H7: TC6 | K7: Specialist Claim- Verify claims are adjudicated successfully and submitted to OFIN for Payment | L7: Same as expected | N7: Pass
H8: TC7 | K8: Referral required- Verify claims are adjudicated successfully and submitted to OFIN for Payment | L8: Same as expected | N8: Pass
H9: TC8 | I9: C131747 | K9: Auth required-Verify claims are adjudicated successfully and submitted to OFIN for Payment | L9: Same as expected | N9: Pass
A10: Referral Circles | H10: TC9 | K10: Referral Logic- Claim where servicing provider is not members PCP but is part of same referral circle as the member's PCP and affiliated to same organization as the members PCP (No referral attached to the claim). Claim is adjudicated successfully and submitted to OFIN for Payment | L10: Same as expected | N10: Not Applicable
H11: TC10 | K11: Referral Logic- Claim where servicing provider is not members PCP and is NOT part of same referral circle as the member's PCP. (No referral attached to the claim), Claim is denied for no referral | L11: Same as expected | N11: Not Applicable
H12: TC11 | I12: C144198 | K12: EOC Claim -Confirm EOC claims are adjudicated properly | L12: Same as expected | N12: Pass
H13: TC12 | I13: C131360 | K13: COB Claim -Confirm COB claims are adjudicated properly | N13: Pass
H14: TC13 | I14: C138929 | K14: Out Of Area Ambulance Claim-Verify out of area ambulance claims are processed and adjudicated appropriately | L14: Same as expected | N14: Pass
H15: TC14 | K15: Urgent Care Claim-Verify urgent care claims are processed and adjudicated appropriately | N15: Pass
H16: TC15 | I16: C138929 | K16: Emergency Claim-Verify urgent/emergency service claims are processed and adjudicated appropriately | N16: Pass
H17: TC16 | I17: C131470 | K17: Accumulator Updates - Verify member accumulator is updated with appropriate DED/OOP dollar amounts | N17: Pass
H18: TC17 | I18: C136731 | K18: Adujstment Scenarios - Verify member reimbursement for overages through UI adjustments and confirm payment request down to OFIN | N18: Not Applicable | S18: tested as part of release 1
H19: TC18 | I19: C147034 & C168004 | K19: EOB and PRA are successfully generated for the claims | L19: Same as expected | N19: Not Applicable | S19: tested as part of release 1
H20: TC19 | I20: C147034 & C168004 | K20: EOB and PRA have the correct information populated- Member & Provider, Claim information, Payment information, Member/Provider responsibility, remark/deny codes | L20: Same as expected | N20: Not Applicable
A21: Clinical- ICUE | H21: TC20 | K21: Referral is successfully submitted from ICUE | L21: Same as expected | N21: Pass | S21: 45305
H22: TC21 | K22: Authorization is successfully submitted from ICUE | L22: Same as expected | N22: Pass | S22: A003300842
H23: TC22 | K23: Dependant Claim- Verify claims are adjudicated successfully and submitted to OFIN for Payment | N23: Pass
K24: Tiered Benefits- Add scnearios | N24: Not Applicable

Sheet PCP Assignment
A1: Application/Component Name | B1: E2E Featrure # (Test Execution) | C1: Domain Feature # | D1: State | E1: Product | F1: Test Case Status | G1: Owner | H1: S.NO# / TC# | I1: Journey | J1: User Experience | K1: Description/Expected Results | L1: Actual Results | M1: Prod Need by Date | N1: Pass/Fail | O1: Executed By | P1: Environment | Q1: Data | R1: Rally Defect# | S1: Tester Comments
H2: TC1 | K2: Auto Assign - Verify in-network PCPs are auto assigned for members enrolled in Signature Value HMO | L2: Same as expected | N2: Pass
H3: TC2 | K3: Direct Assign - Verify PCP can be added via Cirrus UI | L3: Same as expected | N3: Pass | R3: DE1227811 | S3: 112022103102
H4: TC3 | K4: Auto Assign - Verify PCP can be added via B&E Portal | L4: Same as expected | N4: Pass
H5: TC4 | K5: Verify Provider Directory (guest & authenticated) for PCP display and Sorting order | L5: Same as expected | N5: Pass
H6: TC5 | K6: Auto Assign - Verify that member is assigned to PCP with open ended contract date (12-31-9999) | N6: Pass
H7: TC6 | K7: Direct Assign - Verify that if member provided PCP ID has an end date, then PCP is not assigned and an appropriate pcp is selected in it's place | L7: Same as expected | N7: Pass
H8: TC7 | K8: Direct Assign - Member requests an Organization as a PCP. Organization does not have any active Providers affiliated, nor does it have any active Contracts | L8: Same as expected | N8: Pass | S8: 112023758024
H9: TC8 | K9: Direct Assign - Verify PCP can be assigned to member at Org level Member requests an Organization as a PCP. Organization does not have any active Providers affiliated, but does it have an active Contract | L9: Same as expected | N9: Pass | S9: 112021199540
H10: TC9 | K10: Auto Assign - Verify PCP is assigned appropriately based on member's age/gender range | L10: Same as expected | N10: Pass
H11: TC10 | K11: Direct Assign - Female Member age 18 request PCP with Age/Gender M/F/U = 18-999 | L11: Same as expected | N11: Pass
H12: TC11 | K12: Direct Assign - Female Member age 18 request PCP with Age/Gender F = 0-999 | L12: Same as expected | N12: Pass
H13: TC12 | K13: Direct Assign - Verify that if Provider does not meet the age requirements for member's PCP request, then assignment fails and PCP is randomized Female Member Age 1 request PCP with Age/Gender M/F/U = 18-999 | L13: Same as expected | N13: Pass | S13: 112021260393
H14: TC13 | K14: Direct Assign - Male Member age 18 request PCP with Age/Gender M/F/U = 18-999 | L14: Same as expected | N14: Pass
H15: TC14 | K15: Direct Assign - Male Member age 18 request PCP with Age/Gender M = 0-999 | L15: Same as expected | N15: Pass
H16: TC15 | K16: Direct Assign - Male Member Age 1 request PCP with Age/Gender M/F/U = 18-999 | L16: Same as expected | N16: Pass
H17: TC16 | K17: Auto Assign - Verify Newborn member is assigned appropriate PCP upon enrollment based on age if mother's pcp is not appropriate | L17: Same as expected | N17: Pass
H18: TC17 | K18: Auto Assign - Verify Newborn member is assigned to mother's group upon enrollment | L18: Same as expected | N18: Pass | S18: 112022113253
H19: TC18 | K19: Verify ID cards for Group/Org Assignment | L19: Same as expected | N19: Pass
H20: TC19 | K20: Verify ID cards for individual pcp assignment | L20: Same as expected | N20: Pass
H21: TC20 | K21: Direct Assign - Verify pcp assignment using member work address, which is outside from home address service area | L21: Same as expected | N21: Pass
H22: TC21 | K22: Direct Assign - Verify pcp assignment using member home address | L22: Same as expected | N22: Pass
K23: Direct Assign - Verify PCP assignment to staff Model PCP location | L23: Same as expected | N23: Pass | S23: 112021199540
K24: Direct Assign - CA Signature Value HMO member attempts to choose a Signature Value PCP, but lives in a Zip code outside the range of benefit plan service area allowance, then PCP is not assigned and system randomizes a new PCP | L24: Same as expected | N24: Pass
K25: Direct Assign - Verify if member selected PCP is out of Area and not assigned then assignment should fall to manual review Member lives in Fresno, CA, PCP is in Porterville, CA, more than 30 miles from the Members home address | L25: Same as expected | N25: Pass
K26: Direct Assign - Member lives in California and selects a PCP who has active Contracts in California for County A and County B which are contiguous Markets | L26: Same as expected | N26: Pass
K27: Direct Assign - Member lives in California County B and selects a PCP who has active Contracts in California County A and County C | L27: Same as expected | N27: Pass
K28: Member selects a PCP who has a Provider and Network Contract. Member has Capitation in their Benefit Schedule. | L28: Same as expected | N28: Pass
K29: Member selects a PCP who has a Provider and Network Contract. Member does not have Capitation in their Benefit Schedule. | L29: Same as expected | N29: Not Applicable
K30: Member selects a PCP who has a Provider and Network Contract. Member has Capitation in their Benefit Schedule. | L30: Same as expected | N30: Not Applicable
K31: Member selects a PCP who has a Provider and Network Contract. Member does not have Capitation in their Benefit Schedule. | L31: Same as expected | N31: Not Applicable
K32: Risk Member with Signature Value HMO assigned to a Provider in the Network Contract and Roster. Provider Terms and Replacement Provider is sent to reassign the Member. Reassign Provider is a Signature Value HMO Provider in a Network Contract and Roster | L32: Same as expected | N32: Deferred
K33: Risk Only Member with Signature Value HMO assigned to a Provider in the Network Contract and Roster. Provider Terms and Replacement Provider is sent to reassign the Member. Reassign Provider is a Signature Value HMO Provider not in a Network Contract and Roster | L33: Same as expected | N33: Deferred
K34: Direct Assign - Verify member is assigned to appropriate location when assigned to a MCO | L34: Same as expected | N34: Pass | S34: 112022103102
K35: Direct Assign - Verify pcp success and failure messages during direct assignment | L35: Same as expected | N35: Pass
K36: Direct Assign - Verify PCP successful direct assignment along with appropriate reason code is displayed in cirrus | L36: Same as expected | N36: Pass
K37: Direct Assign - Verify that if member provided PCP ID can't be assigned then appropriate reason code is displayed in cirrus and PCP is randomized | L37: Same as expected | N37: Pass | S37: 112022113255
K38: Direct Assign - Verify if PCP is not accepting new patients (provider is accepting existing patients but member is not an existing patient), and member requests PCP direct assignment, then PCP is not assigned and randomization occurs | L38: Same as expected | N38: Deferred
K39: Direct Assign - Verify if PCP is not contracted with Signature Value in the Network Schedule, then PCP is not assigned | L39: Same as expected | N39: Pass
K40: Auto Assign - Verify appropriate network ID is displayed for NICE pcp's | L40: Same as expected | N40: Pass
K41: Auto Assign - Verify that if member's address is updated, then currently assigned pcp needs to be revalidated and updated | L41: Same as expected | N41: Pass
K42: Demographic Term - Verify that member can not direct assign a PCP/location whose address is already termed PCP is termed in Demographics, but has Active Roster and Network Contract with Signature Value HMO Network | L42: Same as expected | N42: Pass
K43: Roster Term - Verify that member can not direct assign a PCP is termed in Roster PCP is termed in Roster, but has another Active Roster and Network Contract with Signature Value HMO Network | L43: Same as expected | N43: Pass
K44: Network Term - PCP has an Active Contract, but is termed with Signature Value HMO, Member requests PCP | L44: Same as expected | N44: Pass
K45: Demographic Term - Verify that if member's current PCP's address is termed, then member is reassigned appropriately | L45: Same as expected | N45: Deferred
K46: Contract Term - Verify that if member's current PCP contract is termed, then member is reassigned an appropriate PCP | L46: Same as expected | N46: Deferred
K47: Contract Term - Verify that member can not direct assign a PCP that has a termed contract | L47: Same as expected | N47: Deferred
K48: Contract Term - PCP is active in Demographics, Active Roster, active in Network Contract, but termed in Provider Contract with Signature Value HMO Network | L48: Same as expected | N48: Deferred
K49: Roster & Demographic Term - Verify that if member is assigned to a group, if an individual pcp within the group leaves (terms address and roster) then member is not reassigned a pcp and remains with medical group. | L49: Same as expected | N49: Deferred
... K58: Direct Assign - Verify that when provider exists on both level 1 and level 3. level 1 provider should get assigned. | L58: Same as expected | N58: Not Applicable

Sheet Rating Population
A1: Application/Component Name | B1: E2E Featrure # (Test Execution) | C1: Domain Feature # | D1: State | E1: Product | F1: Test Case Status | G1: Owner | H1: S.NO# / TC# | I1: Journey | J1: User Experience | K1: Description/Expected Results | L1: Actual Results | M1: Prod Need by Date | N1: Pass/Fail | O1: Executed By | P1: Environment | Q1: Data | R1: Rally Defect# | S1: Tester Comments
H2: TC1 | J2: DSS | K2: Verify group is install successfully with HMO Products (HMO-Migrated from Nice) SIGNATUREVALUE Product | L2: Same as expected | N2: pass
H3: TC2 | K3: Verify group is install successfully with HMO Products (HMO-Migrated from Nice) cover all SIGNATUREVALUE_ALLIANCE product | L3: Same as expected | N3: Pass
H4: TC3 | K4: Verify group is install successfully with HMO Products (HMO-Migrated from Nice) cover all SIGNATUREVALUE_HARMONY product | L4: Same as expected | N4: Pass
H5: TC4 | K5: Verify group is install successfully with HMO Products (HMO-Migrated from Nice) cover all SIGNATUREVALUE_ADVANTAGE products | L5: Same as expected | N5: Pass
H6: TC5 | K6: Verify group is install successfully with HMO products+ PPO (Dual Options) | L6: Same as expected | N6: Pass
H7: TC6 | K7: Verify group is install successfully with HMO Products +Dental+Vision | L7: Same as expected | N7: Pass
H8: TC10 | L8: Same as expected | N8: Pass
H9: TC11 | J9: OBM | K9: Verify group is install successfully with HMO Products (HMO-Migrated from Nice) SIGNATUREVALUE Product | L9: Same as expected | N9: Pass
H10: TC12 | K10: Verify group is install successfully with HMO Products (HMO-Migrated from Nice) cover all SIGNATUREVALUE_ALLIANCE product | L10: Same as expected | N10: Pass
H11: TC13 | K11: Verify group is install successfully with HMO Products (HMO-Migrated from Nice) cover all SIGNATUREVALUE_HARMONY product | L11: Same as expected | N11: Pass
H12: TC14 | K12: Verify group is install successfully with HMO Products (HMO-Migrated from Nice) cover all SIGNATUREVALUE_ADVANTAGE products | L12: Same as expected | N12: Pass
A13: Fulfillment | H13: TC3 | I13: Integrated Open Enrollment Experience Working together to attract membership and set Plan expectations. Coordinated approach to onboarding. Members must be active during enrollment select PCP or a PCP will be assigned by UHC | J13: As a member I am able to receive my health insurance ID card and other fulfillment material | K13: Verify ID Cards are triggered from Cirrus as per the scheduled date | L13: Same as expected | N13: Pass
H14: TC4 | K14: Verify ID cards PDFs are generated in Fiserv as expected with requirements. | L14: Same as expected | N14: Pass
H15: TC5 | K15: Verify PCP name is printed on ID card for individual provider <as applicable> | L15: Same as expected | N15: Pass
H16: TC6 | K16: Verify Provider group name is printed on ID card when PCP is a medical group. <as applicable> | L16: Same as expected | N16: Pass
H17: TC7 | K17: Verify ACO name is printed on ID card when PCP is from the ACO roster <as applicable> | L17: Same as expected | N17: Pass
H18: TC8 | K18: Verify product name, legal entity and logo are displayed on the ID card as expected | L18: Same as expected | N18: Pass
H19: TC9 | K19: Verify Benefits - Benefit Plan - Accumulators - Benefit Deductibles - Deductible Periods are displayed on the ID card as expected | L19: Same as expected | N19: Pass
H20: TC10 | K20: Verify member's first name, middle name, last name and suffix are displayed on Id Card. | L20: Same as expected | N20: Pass
H21: TC11 | K21: Verify member's external id and benefit plan group id matches with Cirrus and displayed. | L21: Same as expected | N21: Pass
H22: TC12 | K22: Verify Member's benefit plan name is printed in the Id Card as expected | L22: Same as expected | N22: Pass
H23: TC13 | K23: Verify rx effective date and member's benefit plan payer id is display. | L23: Same as expected | N23: Pass
H24: TC14 | K24: Verify member's fulfilment product name with network scheduled display | L24: Same as expected | N24: Pass
H25: TC15 | K25: Verify Copays printed on ID card are correct per the benefit plan | L25: Same as expected | N25: Pass
... H34: TC24 | K34: Verify PCP letters are triggered from Cirrus when a new PCP is assigned or updated | L34: Same as expected | N34: Pass
H35: TC26 | I35: Plan Documents | K35: Verify once group is installed sucessfully, events should be created automatlically | L35: Same as expected | N35: Pass | O35: 5537846
H36: TC27 | K36: verify if the events are triggerd sucussfully and its in Complete staus in Cirrus | L36: Same as expected | N36: Pass
H37: TC28 | K37: Verify events are in Archive status in DB once COM360 is done processing | L37: Same as expected | N37: Pass
H38: TC29 | K38: Verify other fulfillment materials (COC, SBC) <as applicable> | L38: Same as expected | N38: Pass
H39: TC30 | K39: Verify benefit language <as applicable> in B360 (for fully insured) | L39: Same as expected | N39: Pass
H40: TC31 | K40: Verify benefit language in B360 vs benefit language in Cirrus | L40: Same as expected | N40: Pass
H41: TC33 | J41: BEACH | K41: Verify benefit language in BEACH application | L41: Same as expected | N41: Pass
H42: TC34 | K42: Verify Coverage Inforamtion in BEACH | L42: Same as expected | N42: Pass
H43: TC35 | K43: Verify we are able to pull plan documents from Coerage or Costs Tab. | L43: Same as expected | N43: Pass

Sheet Carve out
A1: Application/Component Name | B1: E2E Featrure # (Test Execution) | C1: Domain Feature # | D1: State | E1: Product | F1: Test Case Status | G1: Owner | H1: S.NO# / TC# | I1: Journey | J1: User Experience | K1: Description/Expected Results | L1: Actual Results | M1: Prod Need by Date | N1: Pass/Fail | O1: Executed By | P1: Environment | Q1: Data | R1: Rally Defect# | S1: Tester Comments
A2: Carve Out | H2: TC1 | J2: Case install | K2: Case installation through DSS with 2 rx MEDRXDEDTYPE + ICCOPRX (OptumRx Injectables/ICOPP Rx plan) | L2: Same as expected | N2: Pass
H3: TC2 | K3: Case installation through OBM with 2 rx Carveout plan ID | L3: Same as expected | N3: Pass
H4: TC3 | K4: Validate RX benefit plans on UI | L4: Same as expected | N4: Pass
H5: TC4 | J5: Fullfilment | K5: Validate RX Carveout vendor name, phone number, url on benefit documents (COC's and SBC's) | L5: Same as expected | N5: Pass
H6: TC5 | K6: Validate ID Card displays 2 BIN numbers for carveout plan and ICCOP | L6: Same as expected | N6: Pass
H7: TC6 | J7: Portals/Digital | K7: Validate ICCOP plan displayed in provider portal eligibilty file | L7: Same as expected | N7: Pass
H8: TC7 | K8: Validate Acet displays carve‑out vendor name + phone (and URL if supported), and indicates Rx is carved out | L8: Same as expected | N8: Pass | S8: Only shows RX is carved out with ICCOP
H9: TC8 | K9: Validate Acet displays ICOPP/injectables for member benefits | L9: Same as expected | N9: Pass
H10: TC9 | K10: Validate Myuhc ICCOP plan displayed under rx coverage for portal | L10: Same as expected | N10: Deferred | S10: This can be vlidated in R3 if enhancements are made to myuhc
H11: TC10 | K11: Validate member ID card in myuhc | L11: Same as expected | N11: Pass
H12: TC11 | K12: Validate member can access optumRX for ICCOP plan | L12: Same as expected | N12: Pass
H13: TC12 | J13: Claims/Accums | K13: Validate member accums is updated properly in Cirrus | L13: Same as expected | N13: Pass
H14: TC13 | K14: Validate accums exchange with OptumRX for ICCOP plans | L14: Same as expected | N14: Pass | R14: INC49518867
H15: TC14 | K15: Validate proper member detail/claim transfer with OptumRX | L15: Same as expected | N15: Pass
H16: TC15 | J16: Regression | K16: Validate all regression scenarios for all portals, finance, fullfilment where rx plan benefits details exists | L16: Same as expected | N16: Pass
H17: TC16 | K17: Validate all member claims and accum scenarios for RX Carveout mg and members | L17: Same as expected | N17: Pass

Sheet Metrics
A1: PR3- 1/1/22
A2: TC Metrics | B2: Case Inst | C2: Downstream Extract | D2: B&C | E2: Maint | F2: Clm/Clin | G2: DE | H2: Carve out | I2: Rating Population | J2: Integrated Administration | K2: Cal Choice | L2: PCP | M2: Fullfilment | N2: Total
A3: Pass | B3: =COUNTIF('Case Install'!N2:N66,"Pass") -> 64 | C3: =COUNTIF('Downstream Extract'!N1:N294,"Pass") -> 25 | D3: =COUNTIF('Bill&Comm'!N2:N12,"Pass") -> 11 | E3: =COUNTIF(Maint!N2:N44,"Pass") -> 39 | F3: =COUNTIF(ClmsClin!N2:N24,"Pass") -> 17 | G3: =COUNTIF(DE!N2:N93,"Pass") -> 74 | H3: =COUNTIF('Carve out'!N2:N18,"Pass") -> 15 | I3: =COUNTIF('Rating Population'!N2:N43,"Pass") -> 42 | J3: =COUNTIF('Integrated Administration'!N3:N35,"Pass") -> 30 | K3: =COUNTIF('Cal Choice'!N2:N158,"Pass") -> 132 | L3: =COUNTIF('PCP Assignment'!N2:N58,"Pass") -> 43 | M3: =COUNTIF(Fulfillment!N2:N33,"Pass") -> 31 | N3: =SUM(B3:M3) -> 523
A4: Fail | B4: =COUNTIF('Case Install'!N2:N66,"Fail") -> 0 | C4: =COUNTIF('Downstream Extract'!N1:N294,"Fail") -> 0 | D4: =COUNTIF('Bill&Comm'!N2:N12,"Fail") -> 0 | E4: =COUNTIF(Maint!N2:N44,"Fail") -> 0 | F4: =COUNTIF(ClmsClin!N2:N24,"Fail") -> 0 | G4: =COUNTIF(DE!N2:N93,"Fail") -> 0 | H4: =COUNTIF('Carve out'!N2:N19,"Fail") -> 0 | I4: =COUNTIF('Rating Population'!N2:N43,"Fail") -> 0 | J4: =COUNTIF('Integrated Administration'!N3:N35,"Fail") -> 0 | K4: =COUNTIF('Cal Choice'!N2:N158,"Fail") -> 0 | L4: =COUNTIF('PCP Assignment'!N2:N58,"Fail") -> 0 | M4: =COUNTIF(Fulfillment!N2:N33,"Fail") -> 0 | N4: =SUM(B4:M4) -> 0
A5: Deferred | B5: =COUNTIF('Case Install'!N2:N66,"Deferred") -> 0 | C5: =COUNTIF('Downstream Extract'!N1:N294,"Deferred") -> 0 | D5: =COUNTIF('Bill&Comm'!N2:N12,"Deferred") -> 0 | E5: =COUNTIF(Maint!N2:N44,"Deferred") -> 0 | F5: =COUNTIF(ClmsClin!N2:N24,"Deferred") -> 0 | G5: =COUNTIF(DE!N2:N93,"Deferred") -> 3 | H5: =COUNTIF('Carve out'!N2:N20,"Deferred") -> 1 | I5: =COUNTIF('Rating Population'!N2:N43,"Deferred") -> 0 | J5: =COUNTIF('Integrated Administration'!N3:N28,"Deferred") -> 0 | K5: =COUNTIF('Cal Choice'!N2:N158,"Deferred") -> 5 | L5: =COUNTIF('PCP Assignment'!N2:N58,"Deferred") -> 10 | M5: =COUNTIF(Fulfillment!N2:N33,"Deferred") -> 0 | N5: =SUM(B5:M5) -> 19
A6: Not Valid | B6: =COUNTIF('Case Install'!N2:N66,"Not Valid") -> 0 | C6: =COUNTIF('Downstream Extract'!N1:N294,"Not Valid") -> 0 | D6: =COUNTIF('Bill&Comm'!N2:N12,"Not Valid") -> 0 | E6: =COUNTIF(Maint!N2:N44,"Not Valid") -> 0 | F6: =COUNTIF(ClmsClin!N2:N24,"Not Valid") -> 0 | G6: =COUNTIF(DE!N2:N93,"Not Valid") -> 0 | H6: =COUNTIF('Carve out'!N2:N21,"Not Valid") -> 0 | I6: =COUNTIF('Rating Population'!N2:N43,"Not Valid") -> 0 | J6: =COUNTIF('Integrated Administration'!N3:N35,"Not Valid") -> 0 | K6: =COUNTIF('Cal Choice'!N2:N1158,"Not Valid") -> 0 | L6: =COUNTIF('PCP Assignment'!N2:N58,"Not Valid") -> 0 | M6: =COUNTIF(Fulfillment!N2:N33,"Not Valid") -> 0 | N6: =SUM(B6:M6) -> 0
A7: Not Applicable | B7: =COUNTIF('Case Install'!N2:N66,"Not Applicable") -> 1 | C7: =COUNTIF('Downstream Extract'!N1:N294,"Not Applicable") -> 0 | D7: =COUNTIF('Bill&Comm'!N2:N12,"Not Applicable") -> 0 | E7: =COUNTIF(Maint!N2:N44,"Not Applicable") -> 4 | F7: =COUNTIF(ClmsClin!N2:N24,"Not Applicable") -> 6 | G7: =COUNTIF(DE!N2:N93,"Not Applicable") -> 15 | H7: =COUNTIF('Carve out'!N2:N22,"Not Applicable") -> 0 | I7: =COUNTIF('Rating Population'!N2:N43,"Not Applicable") -> 0 | J7: =COUNTIF('Integrated Administration'!N3:N35,"Not Applicable") -> 1 | K7: =COUNTIF('Cal Choice'!N2:N158,"Not Applicable") -> 10 | L7: =COUNTIF('PCP Assignment'!N2:N58,"Not Applicable") -> 4 | M7: =COUNTIF(Fulfillment!N2:N33,"Not Applicable") -> 1 | N7: =SUM(B7:M7) -> 42
A8: In Progress | B8: =COUNTIF('Case Install'!N2:N66,"In Progress") -> 0 | C8: =COUNTIF('Downstream Extract'!N1:N294,"In Progress") -> 0 | D8: =COUNTIF('Bill&Comm'!N2:N12,"In Progress") -> 0 | E8: =COUNTIF(Maint!N2:N44,"In Progress") -> 0 | F8: =COUNTIF(ClmsClin!N2:N24,"In Progress") -> 0 | G8: =COUNTIF(DE!N2:N93,"In Progress") -> 0 | H8: =COUNTIF('Carve out'!N2:N23,"In Progress") -> 0 | I8: =COUNTIF('Rating Population'!N2:N43,"In Progress") -> 0 | J8: =COUNTIF('Integrated Administration'!N3:N35,"In Progress") -> 0 | K8: =COUNTIF('Cal Choice'!N2:N158,"In Progress") -> 0 | L8: =COUNTIF('PCP Assignment'!N2:N58,"In Progress") -> 0 | M8: =COUNTIF(Fulfillment!N2:N33,"In Progress") -> 0 | N8: =SUM(B8:M8) -> 0
A9: No Run (Not Started) | B9: =COUNTIF('Case Install'!N2:N66,"No Run") -> 0 | C9: =COUNTIF('Downstream Extract'!N1:N294,"No Run") -> 0 | D9: =COUNTIF('Bill&Comm'!N2:N12,"No Run") -> 0 | E9: =COUNTIF(Maint!N2:N44,"No Run") -> 0 | F9: =COUNTIF(ClmsClin!N2:N24,"No Run") -> 0 | G9: =COUNTIF(DE!N2:N93,"No Run") -> 0 | H9: =COUNTIF('Carve out'!N2:N24,"No Run") -> 0 | I9: =COUNTIF('Rating Population'!N2:N43,"No Run") -> 0 | J9: =COUNTIF('Integrated Administration'!N3:N35,"No Run") -> 0 | K9: =COUNTIF('Cal Choice'!N2:N158,"No Run") -> 0 | L9: =COUNTIF('PCP Assignment'!N2:N58,"No Run") -> 0 | M9: =COUNTIF(Fulfillment!N2:N33,"No Run") -> 0 | N9: =SUM(B9:M9) -> 0
A10: Total Test Scripts | B10: =SUM(B3:B9) -> 65 | C10: =SUM(C3:C9) -> 25 | D10: =SUM(D3:D9) -> 11 | E10: =SUM(E3:E9) -> 43 | F10: =SUM(F3:F9) -> 23 | G10: =SUM(G3:G9) -> 92 | H10: =SUM(H3:H9) -> 16 | I10: =SUM(I3:I9) -> 42 | ... N10: =SUM(N3:N9) -> 584
A13: Market Event | B13: Not Started | C13: In progress | D13: Passed | E13: Failed | F13: On Hold | G13: N/A, Not Valid, Deferred | H13: Total | I13: % Executed | J13: % Passed | K13: Start Date | L13: Finish Date | M13: Current Defects
A14: Case Install | B14: =B9 -> 0 | C14: =B8 -> 0 | D14: =B3 -> 64 | E14: =B4 -> 0 | F14: 0 | G14: =SUM(B5:B7) -> 1 | H14: =SUM(B14:G14) -> 65 | I14: =IF((H14-G14>0),SUM(D14:F14)/(H14-G14),"0.0%") -> 1 | J14: =IF((D14>0),(D14)/(H14-G14),"0.0%") -> 1
A15: Downstream Extract | B15: =C9 -> 0 | C15: =C8 -> 0 | D15: =C3 -> 25 | E15: =C4 -> 0 | F15: 0 | G15: =SUM(C5:C7) -> 0 | H15: =SUM(B15:G15) -> 25 | I15: =IF((H15-G15>0),SUM(D15:F15)/(H15-G15),"0.0%") -> 1 | J15: =IF((D15>0),(D15)/(H15-G15),"0.0%") -> 1
A16: Billing & Commission | B16: =D9 -> 0 | C16: =D8 -> 0 | D16: =D3 -> 11 | E16: =D4 -> 0 | F16: 0 | G16: =SUM(D5:D7) -> 0 | H16: =SUM(B16:G16) -> 11 | I16: =IF((H16-G16>0),SUM(D16:F16)/(H16-G16),"0.0%") -> 1 | J16: =IF((D16>0),(D16)/(H16-G16),"0.0%") -> 1
A17: Member Maintenance | B17: =E9 -> 0 | C17: =E8 -> 0 | D17: =E3 -> 39 | E17: =E4 -> 0 | F17: 0 | G17: =SUM(E5:E7) -> 4 | H17: =SUM(B17:G17) -> 43 | I17: =IF((H17-G17>0),SUM(D17:F17)/(H17-G17),"0.0%") -> 1 | J17: =IF((D17>0),(D17)/(H17-G17),"0.0%") -> 1
A18: Claims & Clinical | B18: =F9 -> 0 | C18: =F8 -> 0 | D18: =F3 -> 17 | E18: =F4 -> 0 | F18: 0 | G18: =SUM(F5:F7) -> 6 | H18: =SUM(B18:G18) -> 23 | I18: =IF((H18-G18>0),SUM(D18:F18)/(H18-G18),"0.0%") -> 1 | J18: =IF((D18>0),(D18)/(H18-G18),"0.0%") -> 1
A19: Digital/Constituent Services | B19: =G9 -> 0 | C19: =G8 -> 0 | D19: =G3 -> 74 | E19: =G4 -> 0 | F19: 0 | G19: =SUM(G5:G7) -> 18 | H19: =SUM(B19:G19) -> 92 | I19: =IF((H19-G19>0),SUM(D19:F19)/(H19-G19),"0.0%") -> 1 | J19: =IF((D19>0),(D19)/(H19-G19),"0.0%") -> 1
A20: PCP Assignment | B20: =L9 -> 0 | C20: =L8 -> 0 | D20: =L3 -> 43 | E20: =L4 -> 0 | F20: 0 | G20: =SUM(L5:L7) -> 14 | H20: =SUM(B20:G20) -> 57 | I20: =IF((H20-G20>0),SUM(D20:F20)/(H20-G20),"0.0%") -> 1 | J20: =IF((D20>0),(D20)/(H20-G20),"0.0%") -> 1
A21: Fullfilment | B21: =M9 -> 0 | C21: =M8 -> 0 | D21: =M3 -> 31 | E21: =M4 -> 0 | F21: 0 | G21: =SUM(M5:M7) -> 1 | H21: =SUM(B21:G21) -> 32 | I21: =IF((H21-G21>0),SUM(D21:F21)/(H21-G21),"0.0%") -> 1 | J21: =IF((D21>0),(D21)/(H21-G21),"0.0%") -> 1
A22: Total | B22: =SUM(B14:B21) -> 0 | C22: =SUM(C14:C21) -> 0 | D22: =SUM(D14:D21) -> 304 | E22: =SUM(E14:E21) -> 0 | F22: =SUM(F14:F21) -> 0 | G22: =SUM(G14:G21) -> 44 | H22: =SUM(H14:H21) -> 348 | I22: =IF((H22-G22>0),SUM(D22:F22)/(H22-G22),"0.0%") -> 1 | J22: =IF((D22>0),(D22)/(H22-G22),"0.0%") -> 1
A25: Market Event | B25: Not Started | C25: In progress | D25: Passed | E25: Failed | F25: On Hold | G25: N/A, Not Valid, Deferred | H25: Total | I25: % Executed | J25: % Passed | K25: Start Date | L25: Finish Date | M25: Current Defects
A26: Cal Choice | B26: =K9 -> 0 | C26: =K8 -> 0 | D26: =K3 -> 132 | E26: =K4 -> 0 | F26: 0 | G26: =SUM(K5:K7) -> 15 | H26: =SUM(B26:G26) -> 147 | I26: =IF((H26-G26>0),SUM(D26:F26)/(H26-G26),"0.0%") -> 1 | J26: =IF((D26>0),(D26)/(H26-G26),"0.0%") -> 1
A27: Rating Population | B27: =I9 -> 0 | C27: =I8 -> 0 | D27: =I3 -> 42 | E27: =I4 -> 0 | F27: 0 | G27: =SUM(I5:I7) -> 0 | H27: =SUM(B27:G27) -> 42 | I27: =IF((H27-G27>0),SUM(D27:F27)/(H27-G27),"0.0%") -> 1 | J27: =IF((D27>0),(D27)/(H27-G27),"0.0%") -> 1
A28: Integrated Administration | B28: =J9 -> 0 | C28: =J8 -> 0 | D28: =J3 -> 30 | E28: =J4 -> 0 | F28: 0 | G28: =SUM(J5:J7) -> 1 | H28: =SUM(B28:G28) -> 31 | I28: =IF((H28-G28>0),SUM(D28:F28)/(H28-G28),"0.0%") -> 1 | J28: =IF((D28>0),(D28)/(H28-G28),"0.0%") -> 1
A29: Carve out | B29: =H9 -> 0 | C29: =H8 -> 0 | D29: =H3 -> 15 | E29: =H4 -> 0 | F29: 0 | G29: =SUM(H5:H7) -> 1 | H29: =SUM(B29:G29) -> 16 | I29: =IF((H29-G29>0),SUM(D29:F29)/(H29-G29),"0.0%") -> 1 | J29: =IF((D29>0),(D29)/(H29-G29),"0.0%") -> 1 | M29: INC49518867
A30: Total | B30: =SUM(B26:B29) -> 0 | C30: =SUM(C26:C29) -> 0 | D30: =SUM(D26:D29) -> 219 | E30: =SUM(E26:E29) -> 0 | F30: =SUM(F26:F29) -> 0 | G30: =SUM(G26:G29) -> 17 | H30: =SUM(H26:H29) -> 236 | I30: =IF((H30-G30>0),SUM(D30:F30)/(H30-G30),"0.0%") -> 1 | J30: =IF((D30>0),(D30)/(H30-G30),"0.0%") -> 1

Sheet Cal Choice
A1: Application/Component Name | B1: E2E Featrure # (Test Execution) | C1: Domain Feature # | D1: State | E1: Product | F1: Test Case Status | G1: Owner | H1: S.NO# / TC# | I1: Journey | J1: User Experience | K1: Description/Expected Results | L1: Actual Results | M1: Prod Need by Date | N1: Pass/Fail | O1: Executed By | P1: Environment | Q1: Data | R1: Rally Defect# | S1: Tester Comments
F2: Designed | K2: Case Install | L2: Same as expected | N2: Pass
F3: Designed | H3: TC1 | J3: Group | K3: Verify that a Parent Group with Organization Type “Corporation” and CalChoice Child Member Group can be affiliated with Member Group Affiliation Type “Third Party Administrator” using DSS Parent group will be cerated manuly , need to know how we are going to Child group (Migrated trhough MTT?) | L3: Same as expected | N3: Pass
F4: Designed | H4: TC2 | K4: Verify that a Parent Group with Organization Type “Corporation” and CalChoice Child Member Group can be affiliated with Member Group Affiliation Type “Third Party Administrator” using Astra Parent group will be cerated manuly , need to know how we are going to Child group (Migrated trhough MTT?) | L4: Same as expected | N4: Pass
F5: Designed | H5: TC3 | J5: member | K5: verify that when a member is enrolled with benefit status = COBRA, the Continuation Effective Date and Expiration Date are displayed on the Cirrus UI. | L5: Same as expected | N5: Pass
J6: member | K6: Member through Astra | L6: Same as expected | N6: Pass
F7: Designed | K7: Fulfillment- | L7: Same as expected
F8: Designed | H8: TC4 | J8: ID Card | K8: Generat using UHC child group ID | L8: Same as expected | N8: Pass
F9: Designed | H9: TC6 | J9: Fullfillment documents | L9: Same as expected | N9: Pass
F10: Designed | H10: TC7 | J10: Parent Member group | L10: Same as expected | N10: Pass
F11: Designed | H11: TC8 | J11: SBC | K11: Create | L11: Same as expected | N11: Pass
F12: Designed | H12: TC9 | J12: SBC NODA | K12: Suppress | L12: Same as expected | N12: Pass
F13: Designed | H13: TC10 | J13: Group HANBOOK | K13: Suppress | L13: Same as expected | N13: Pass
F14: Designed | H14: TC11 | J14: Mmeber Handbook | K14: Suppress | L14: Same as expected | N14: Pass
F15: Designed | H15: TC12 | L15: Same as expected | N15: Pass
F16: Designed | H16: TC13 | J16: Child Member group | L16: Same as expected | N16: Pass
F17: Designed | H17: TC14 | J17: SBC | K17: Suppress | L17: Same as expected | N17: Pass
F18: Designed | H18: TC15 | J18: Group HANBOOK | K18: Suppress | L18: Same as expected | N18: Pass
F19: Designed | H19: TC16 | J19: Member fulfillments | L19: Same as expected | N19: Pass
F20: Designed | H20: TC17 | J20: Member HIPPA notification(POLC/COBRA/AB1401) | K20: Suppress | L20: Same as expected | N20: Pass
F21: Designed | H21: TC18 | J21: All other member level letters/notification | K21: Create (ID card follows the standard process and template) | L21: Same as expected | N21: Pass
F22: Designed | H22: TC19 | J22: Member Handbook NODA | K22: Suppress | L22: Same as expected | N22: Pass
F23: Designed | H23: TC20 | J23: Member Handbook | K23: Suppress | L23: Same as expected | N23: Pass
F24: Designed | K24: Billing & Commission | L24: Same as expected
F25: Designed | H25: TC21 | J25: BRMS | K25: Verfiy FTS is able to consume PCMT | L25: Same as expected | N25: Pass
F26: Designed | H26: TC22 | K26: Verify if we can see Member groups in Invoices | L26: Same as expected | N26: Pass
F27: Designed | H27: TC23 | K27: Verify if we can see All plans in invoices | L27: Same as expected | N27: Pass
F28: Designed | H28: TC24 | K28: Verify if can see Members in Invoices | L28: Same as expected | N28: Pass
F29: Designed | H29: TC25 | K29: Verify if based on the billing schedule on our group Billing calculation is correct. | L29: Same as expected | N29: Pass
F30: Designed | H30: TC26 | K30: 2 Bill schedules: 1 for premium + commissions, the other for commissions adjustment | L30: Same as expected | N30: Pass
F31: Designed | H31: TC27 | K31: New bill schedule with new bill item type will be created to represent the commissions adjustment | L31: Same as expected | N31: Pass
F32: Designed | H32: TC28 | J32: BASICS | K32: Commission is paid by CalChoice Parent, not USP. | L32: Same as expected | N32: Pass
F33: Designed | H33: TC29 | K33: USP has no involvement with brokers or commission payment | L33: Same as expected | N33: Pass
F34: Designed | J34: Case Effective Scope | L34: Same as expected
F35: Designed | K35: Member Maintenance - Cirrus | L35: Same as expected
F36: Designed | H36: TC30 | J36: Cirrus Validation - Member Group | K36: Verify if we are able to Term a Member Group | L36: Same as expected | N36: Pass
F37: Designed | H37: TC31 | K37: Verify if we are able to Cancel a Member Group | L37: Same as expected | N37: Pass
F38: Designed | H38: TC32 | K38: Verify if we are able to Reinstate a Member Group | L38: Same as expected | N38: Pass
F39: Designed | H39: TC33 | K39: Verify if we are able to update Member Group- Demographics, plan information | L39: Same as expected | N39: Pass
F40: Designed | H40: TC34 | K40: Verify if we are able to retro term a Member Group | L40: Same as expected | N40: Pass
F41: Designed | H41: TC35 | K41: Verify if we are able to retro reinstate a Member Group | L41: Same as expected | N41: Pass
F42: Designed | H42: TC36 | K42: Verify if we are able to retro change a plan to Member Group | L42: Same as expected | N42: Pass
F43: Designed | H43: TC37 | J43: Cirrus Validation - Membership | K43: Verify if we are able to add a dependent | L43: Same as expected | N43: Pass
F44: Designed | H44: TC38 | K44: Verify if we are able to term a Member | L44: Same as expected | N44: Pass
F45: Designed | H45: TC39 | K45: Verify if we are able to reinstate a Member | L45: Same as expected | N45: Pass
F46: Designed | H46: TC40 | K46: Verify if we are able to move Member to COBRA | L46: Same as expected | N46: Pass
F47: Designed | H47: TC41 | K47: Verify if we are able to update Member demographics | L47: Same as expected | N47: Pass
F48: Designed | H48: TC42 | K48: Verify if we are able to retro add Member with dependent | L48: Same as expected | N48: Pass
F49: Designed | H49: TC43 | K49: Verify if we are able to retro term a Member | L49: Same as expected | N49: Pass
F50: Designed | H50: TC44 | K50: Verify if we are able to retro reinstate a Member | L50: Same as expected | N50: Pass
F51: Designed | H51: TC45 | K51: Verify if we are able to retro change a plan to Member | L51: Same as expected | N51: Pass
F52: Designed | K52: B&E Portal (CalChoice only can access the portal as an internal user, not as an employer user), however there is no impact to the portal for CalChoice, and may be test only. | L52: Same as expected
A53: Broker & Employer Portal | H53: TC46 | I53: Integrated Open Enrollment Experience- Working together to attract membership and set Plan expectations. Members must be active during enrollment select PCP or a PCP will be assigned by UHC | J53: As an Employer group I should be able to add, change and update my employee information -- B&E | K53: Verify Employer group is able to login to B&E Portal/ UHCeServices.com | L53: Same as expected | N53: Pass
H54: TC47 | K54: Verify Employer group should be able to enroll members | L54: Same as expected | N54: Pass
H55: TC48 | K55: Verify as a Employer group I should be able to see my group's information-Demographics and plans | L55: Same as expected | N55: Pass
H56: TC49 | K56: Verify as a Employer group I should be able to see my billing information | L56: Same as expected | N56: Pass
H57: TC50 | K57: Verify as a Broker I should be able to see my commission statement | L57: Same as expected | N57: Pass
H58: TC51 | K58: Verify as a Employer group I should be able to see my COC | L58: Same as expected | N58: Pass
H59: TC52 | K59: Verify as a Employer group I should be able to see my subscriber and member list | L59: Same as expected | N59: Pass
H60: TC53 | K60: Verify as a Employer group I should be able to see my employee information | L60: Same as expected | N60: Pass
H61: TC54 | K61: Verify we are able to search PCP for Products requring PCP | L61: Same as expected | N61: Pass
H62: TC55 | K62: Verify if we are able to add a dependent | L62: Same as expected | N62: Pass | O62: 112031413628
H63: TC56 | K63: Verify if we are able to term a Member | L63: Same as expected | N63: Pass | O63: 112027981701
H64: TC58 | K64: Verify if we are able to update Member demographics | L64: Same as expected | N64: Pass | O64: 112028002003
H65: TC59 | K65: Verify if we are able to Add Member PCP | L65: Same as expected | N65: Pass
H66: TC60 | K66: Verify if the Ability for NICE Groups to view, Plan Rates , view Benefits & Plan Information | L66: Same as expected | N66: Pass
H67: TC61 | K67: Verify we are able to view member ID cards | L67: Same as expected | N67: Pass
F68: Designed | K68: MyUHC
A69: myUHC | C69: NICE | D69: CA | F69: Designed | H69: TC65 | J69: Dashboard | K69: As a member we are able to Register a member in MyUHC | L69: Same as expected | N69: Pass
C70: NICE | D70: CA | F70: Designed | H70: TC66 | K70: As a member on a gated plan, I have the ability to view any referrals submitted by my PCP | L70: Same as expected | N70: Not Applicable
C71: NICE | D71: CA | F71: Designed | H71: TC67 | K71: As a member on gated plan, I have the ability to view/add/update my PCP on the dashboard when logging into myuhc | L71: Same as expected | N71: Pass
C72: NICE | D72: CA | F72: Designed | H72: TC68 | K72: As a member, on a Non-Gated Plan, although I do not require PCP, I have the ability to add/update a PCP on the dashboard when logging into myuhc | L72: Same as expected | N72: Not Applicable
C73: NICE | D73: CA | F73: Designed | H73: TC69 | K73: As a member, I have the ability to view my Individual/Family Deductible & OOP Max accumulators when logging into myuhc | L73: Same as expected | N73: Pass
C74: NICE | D74: CA | F74: Designed | H74: TC70 | K74: As a member, I have the ability to view recently submitted claims on the dashboard when logging into myuhc | L74: Same as expected | N74: Pass
C75: NICE | D75: CA | F75: Designed | H75: TC71 | K75: As a member, I have the ability to view my ID Card Modal window based on the coverage I am enrolled in (Medical, Dental, Vision) | L75: Same as expected | N75: Pass
C76: NICE | D76: CA | F76: Designed | H76: TC72 | J76: "Find Price & Care" page | K76: As a member member can view/update pcp selection on find care page | L76: Same as expected | N76: Pass
C77: NICE | D77: CA | F77: Designed | H77: TC73 | K77: As a member pcp assignment intial assigmnet and update can be done in MYUHC | L77: Same as expected | N77: Pass
C78: NICE | D78: CA | F78: Designed | H78: TC74 | K78: As a member , I have the ability to view INN primary care providers offered in my plan by selecting Primary Care Physicians | L78: Same as expected | N78: Pass
C79: NICE | D79: CA | F79: Designed | H79: TC75 | K79: As a member on a gated plan, any providers that require a referral will display an alerting me that a referral is required. | L79: Same as expected | N79: Pass
C80: NICE | D80: CA | F80: Designed | H80: TC76 | K80: As a member, I have the ability to search by speciality type and view INN providers that cover services for the speciality selected (Example: Cardiologist) | L80: Same as expected | N80: Pass
C81: NICE | D81: CA | F81: Designed | H81: TC77 | K81: As a member on plan w/ tiering applicable to (PCP/Specialists), providers designated as Tier 1 will display with an icon on the top of the page when accessing an authenticated experience of the directory | L81: Same as expected | N81: Not Applicable
C82: NICE | D82: CA | F82: Designed | H82: TC78 | K82: As a member, I have the ability to select an INN provider and receive a cost estimate based on my benefits for the service covered. | L82: Same as expected | N82: Pass
C83: NICE | D83: CA | F83: Designed | H83: TC79 | K83: As a member on a Level Funded plan, I have the ability to Access to Healthiest You when selecting Virtual Care | L83: Same as expected | N83: Not Applicable
C84: NICE | D84: CA | F84: Designed | H84: TC80 | K84: As a member, I have the ability to view behavioral health providers in my network (Ex: Psychiatrist, Psychologists, etc.) | L84: Same as expected | N84: Pass
C85: NICE | D85: CA | F85: Designed | H85: TC83 | J85: Coverage & Benefits Page | K85: As a member Member can view benefits and coverage on coverage & benefits page | L85: Same as expected | N85: Pass
C86: NICE | D86: CA | F86: Designed | H86: TC84 | K86: As a member, I am able to view view copays for major level services covered in my plan (PCP, Specialist, ER Visit, Virtual Visit, Urgent Care Visit) | L86: Same as expected | N86: Pass
C87: NICE | D87: CA | F87: Designed | H87: TC85 | K87: As a member, when selecting view all medical coverage I can view INN & OON benefit language for benefits included in my plan (Ex:Diabetic Services, Behavioral Health Outpatient – Physicians Office, Hearing Aids) | L87: Same as expected | N87: Pass
C88: NICE | D88: CA | F88: Designed | H88: TC86 | K88: As a member, I am able to view Mental Health Common Services offered in my plan | L88: Same as expected | N88: Pass
C89: NICE | D89: CA | F89: Designed | H89: TC87 | K89: As a member on a UHC fully Insured plan, I am able to access Mental Health Hub to view information on mental health programs offered in my plan (Ex: AbleTo, Sanvello Program) | L89: Same as expected | N89: Pass
F90: Designed | H90: TC91 | K90: Validate Edit PCP options and navigation. | L90: Same as expected | N90: Pass
C91: NICE | D91: CA | F91: Designed | H91: TC92 | K91: As a member, I have the ability to view documents and forms issued to me based on my coverage (Ex: IRS Tax forms, SBC, COC,SPD) for the plans that I am enrolled in | L91: Same as expected | N91: Pass
C92: NICE | D92: CA | F92: Designed | H92: TC93 | J92: Claims & Account | K92: As a member member can submit a claim from claim&account page | L92: Same as expected | N92: Pass | O92: Cirrus Claim ID: 1637442488
C93: NICE | D93: CA | F93: Designed | H93: TC94 | K93: As a member that the User Experience for "NI" BoB should mirror "UH" BoB member experience on USP | L93: Same as expected | N93: Pass
C94: NICE | D94: CA | F94: Designed | H94: TC95 | K94: As a member that member can navigate to Claim & Account page and view payment details based on service provided (Ex: Total Amount, Plan Paid, Member Responsibility) | L94: Same as expected | N94: Pass
C95: NICE | D95: CA | F95: Designed | H95: TC96 | K95: As a member that member can navigate to Claim & Account page and view explanation of benefits for the services incurred. | L95: Same as expected | N95: Pass
C96: NICE | D96: CA | F96: Designed | H96: TC97 | K96: As a member, I am able to view all claims and filter by Date of Service as part of my search | L96: Same as expected | N96: Pass
C97: NICE | D97: CA | F97: Designed | H97: TC98 | K97: As a member, when selecting a Claim, I am able to view payment details based on service provided (Ex: Total Amount, Plan Paid, Member Responsibility) | L97: Same as expected | N97: Pass
C98: NICE | D98: CA | F98: Designed | H98: TC99 | K98: As a member, I have the ability to view my prior authorizations submitted by my provider in the top right hand corner of the claims page | L98: Same as expected | N98: Not Applicable
C99: NICE | D99: CA | F99: Designed | H99: TC100 | K99: As a member, I have the ability to view my current Medical Account Summary (Deductible/OOP max) reflecting an accurate representation based on my claims. If I am on a plan with tiered accumulators, I will be able to select Tier 1 vs INN Accumulators in a dropdown to see my progress for each. | L99: Same as expected | N99: Pass
C100: NICE | D100: CA | F100: Designed | H100: TC101 | K100: As a member, I have the ability to submit a claim reimbursment form | L100: Same as expected | N100: Pass
...

Sheet Integrated Administration
A1: Application/Component Name | B1: E2E Featrure # (Test Execution) | C1: Domain Feature # | D1: State | E1: Product | F1: Test Case Status | G1: Owner | H1: S.NO# / TC# | I1: Journey | J1: User Experience | K1: Description/Expected Results | L1: Actual Results | M1: Prod Need by Date | N1: Pass/Fail | O1: Executed By | P1: Environment | Q1: Data | R1: Rally Defect# | S1: Tester Comments
K2: Case Install | L2: Same as expected
H3: TC1 | J3: Enrollment | K3: Verify that Solaris to OBM integration works correctly. | L3: Same as expected | N3: Pass
H4: TC2 | J4: Enrollment | K4: Verify that ACIS publish sends data to ACIS. | L4: Same as expected | N4: Pass
H5: TC3 | J5: Enrollment | K5: Verify that USP publish sends data to Cirrus. | L5: Same as expected | N5: Pass
H6: TC4 | J6: Enrollment | K6: Verify that platform comparisons are handled appropriately. | L6: Same as expected | N6: Pass
H7: TC5 | J7: Enrollment | K7: Verify that SACI ID is sent when ACIS and USP policies are active. | L7: Same as expected | N7: Pass
H8: TC6 | J8: Enrollment | K8: Verify that AC2 ID is sent when multiple ACIS policies are active with USP. | L8: Same as expected | N8: Pass
H9: TC7 | J9: Enrollment | K9: Verify that CBC ID is sent when multiple USP MG IDs are active. | L9: Same as expected | N9: Pass
H10: TC8 | J10: Enrollment | K10: Verify that the correct External ID label is displayed in GEF based on migration scenario. | L10: Same as expected | N10: Pass
H11: TC9 | J11: Enrollment | K11: Verify that eligibility for HMO in USP and PPO in ACIS is accessible under a single login. | L11: Same as expected | N11: Pass
H12: TC10 | J12: Enrollment | K12: Verify that PCP selection is validated in real time in B&E portal and MyUHC. | L12: Same as expected | N12: Pass
K13: Verify that the group is installed with Active ACIS and USP platforms via OBM. We will only see NICE connected to USP; for ACIS, we do not have access. | L13: Same as expected | N13: Pass
J14: Custom Riders | K14: Validate that the group is installed correctly with the ACIS Customer ID Number on the page under “Member Group External ID | L14: Same as expected | N14: Pass
H15: TC11 | J15: Enrollment | K15: Verify that membership counts are accurate and not duplicated. | L15: Same as expected | N15: Pass
J16: Billing | N16: Pass
H17: TC12 | J17: Billing | K17: Verify that a consolidated invoice displays all products. | L17: Same as expected | N17: Pass
H18: TC13 | J18: Billing | K18: Verify that a single payment is processed across all products. | L18: Same as expected | N18: Pass
J19: Broker Commission | N19: Pass
H20: TC14 | J20: Broker Commission | K20: Verify that a consolidated commission statement includes all products. | L20: Same as expected | N20: Pass
H21: TC15 | J21: Broker Commission | K21: Verify that brokers can access commission data with a single login. | L21: Same as expected | N21: Pass
J22: Fulfillment | N22: Pass
H23: TC16 | J23: Fulfillment | K23: Verify that separate policy documents are generated for each product. | L23: Same as expected | N23: Pass
H24: TC17 | J24: Fulfillment | K24: Verify that ID cards are generated correctly for HMO members. | L24: Same as expected | N24: Pass
J25: ACET
H26: TC 18 | J26: Constituent Service | K26: Ensure member data accessible via ACET | L26: Same as expected | N26: Pass
H27: TC 19 | J27: Constituent Service | K27: Validate consolidated view for employer and broker portals | L27: Same as expected | N27: Pass
J28: IA Changes | K28: As a member service advocate, when I search for a member who has coverage on a platform other than Cirrus, I see the member’s information in the search results, And an informational message stating “Member does not have a Cirrus plan; blank fields are expected.” | N28: Not Applicable
J29: MYUHC | K29: MYUHC | N29: Pass
J30: IA Changes | K30: As a member, If I want to edit my PCP details, I am able to select “Change Office Location for PCP Visits” and navigate to the location selection page. | L30: Same as expected | N30: Pass
J31: IA Changes | K31: As a member,If I want to assign my PCP to other family members, I am able to select “Assign this PCP to Other Family Members”, navigate to the location selection page, and then to the family member selection page. | L31: Same as expected | N31: Pass
J32: IA Changes | K32: As a member, If I belong to E&I NICE population, I do not see Premium Care Physician (blue heart) in provider search results or filters. | L32: Same as expected | N32: Pass
J33: IA Changes | K33: As a member, If I change my PCP or network affiliation, I see a confirmation screen with header “Confirm primary care physician or network affiliation change”, and no Medical Group ID displayed. | L33: Same as expected | N33: Pass
J34: IA Changes | K34: As a member, If I view a hospital’s details, I am able to see Network Affiliations in the Overview section and per location in the Locations tab, with “Not available” shown when data is missing. | L34: Same as expected | N34: Pass
J35: IA Changes | K35: If my PCP is part of a staff model, I see “Your primary care provider (PCP)” banner for all PCPs in my network and staff location, and PCP Dashboard displays the staff model name. | L35: Same as expected | N35: Deferred | O35: its pcp rule to assign staffmodel we can assign 5/1 eff pcp

Sheet Reporting
A1: Application/Component Name | B1: E2E Featrure # (Test Execution) | C1: Domain Feature # | D1: State | E1: Product | F1: Test Case Status | G1: Owner | H1: S.NO# / TC# | I1: Journey | J1: User Experience | K1: Description/Expected Results | L1: Actual Results | M1: Prod Need by Date | N1: Pass/Fail | O1: Executed By | P1: Environment | Q1: Data | R1: Rally Defect# | S1: Tester Comments
A2: Reporting | L2: Same as expected | N2: No Run
L3: Same as expected | N3: No Run
L4: Same as expected | N4: No Run
L5: Same as expected | N5: No Run
L6: Same as expected | N6: No Run
L7: Same as expected | N7: No Run
L8: Same as expected | N8: No Run
L9: Same as expected | N9: No Run
L10: Same as expected | N10: No Run
L11: Same as expected | N11: No Run
L12: Same as expected | N12: No Run

Sheet Defects
B1: Defect ID | C1: Description | D1: Owner | E1: Status | G1: Comments
A2: 1 | B2: DE1221906 | C2: NICE Rel 2 || Benefit Bundle Match error | E2: Closed
A3: 2 | B3: DE1218502 | C3: DSS - Rating Pop Group Creation Fails with Bundle Assembly || NICE R2 | E3: Closed
A4: 3 | B4: DE1227811 | C4: Member not randomizing when member is enrolled via member entry and no provider is chosen and member requested is "yes" or "no" | E4: Closed
A5: 4 | B5: DE1250128 | C5: Extract Data Missing in CloudBerry 1/13/2026 | D5: Jawahar Soni | E5: Closed | G5: Alla, Ramesh - (ramesh.alla@optum.com) is looking into it. Fixed 1/20/2026
A6: 5 | B6: DE1251142 | C6: NICE Release 2 | Smart assignment failing for Signature Harmony - Triage needed | D6: G Hari Prasad | E6: Closed
A7: 6 | B7: DE1252513 | C7: we are not able to reinstate a Member | D7: Jawahar Soni | E7: Closed
A8: 7 | C8: BnE Stopped working - Asked for the Existing Defect1/29/2026 | D8: Jawahar Soni | E8: Closed | G8: Bne Non Prod Team
A9: 8 | B9: DE1262505 | C9: During NICE R2 testing, the referral item appears on the Dashboard as expected. However, clicking the referral hyperlink redirects the user back to the Dashboard rather than navigating to the Referral Details view. This blocks validation of the scenario “ability to view any referrals submitted | D9: Janeshwar Chowdhary | E9: Closed | G9: myUHC team
A10: 9 | B10: DE1262522 | C10: Currently, the SSO functionality is not working, and the user is unable to reach the Vision Portal. | D10: Janeshwar Chowdhary | E10: Closed | G10: myUHC team
A11: 10 | B11: DE1262623 | C11: Member Reinstate into Cobra is Failing. Completed. 2/9/2026 | D11: Jawahar Soni | E11: Closed | G11: Bne Non Prod Team
A12: 11 | B12: DE1262631 | C12: Incorrect Termination Status in BnE | D12: Jawahar Soni | E12: Closed | G12: Bne Non Prod Team
A13: 12 | B13: DE1275253 | C13: Unable to Submit Claim for Cal Choice Member – “Date is out of coverage” Error Despite Valid Coverage | D13: Janeshwar Chowdhary | E13: Closed | G13: myUHC team | H13: Cal choice
A14: 13 | B14: DE1275233 | C14: Provider Details Not Displayed on MyUHC Home Page for Cal Choice Member | D14: Janeshwar Chowdhary | E14: Closed | G14: myUHC team | H14: Cal choice
A15: 14 | B15: DE1283191 | C15: E2E PET New Business - Nice2:Unable to Move Member to COBRA | D15: Jawahar Soni | E15: Closed | G15: Bne Non Prod Team
A16: 16 | B16: DE1283193 | C16: Print Confirmation button missing label on Termination Confirmation page/ | D16: Jawahar Soni | E16: Closed | F16: Nice Rel2 | G16: Bne Non Prod Team. As this is not impacting this project, Tag #US10061679 removed.
A17: 17 | B17: DE1304848 | C17: Update UHCBENEFITIDs for OptumRxDirect and Caremark in OBM (Nice Rel2 CarveOut Testing). 4/20/2026 Closed | D17: Samir from Renewals | E17: Closed | F17: Nice Rel2 CarveOut Testing | G17: OBM Team: In OBM, the value is currently configured as CarveOut_OptumRx Direct; however, it should be CarveOut_OptumRxDirect. The only difference is the additional space, which needs to be corrected. Same for Carve-Out Rx vs CarveOut_Caremark
A18: 18 | B18: DE1309820 | C18: Nice Rel2- CarveOut Testing: Active Member Holds: MBBG #DE1313032 opened by QIB | D18: Jawahar Soni | E18: In Progress | F18: Nice Rel2 CarveOut Testing
A19: 19 | B19: DE1310222 | C19: Medical Handbook Request Status Error: ERR62302 - ENROLL_PRO_METHOD | D19: Jawahar Soni | E19: Closed | F19: Nice Rel2 CarveOut & Nice 3 CaLPERS Testing | G19: When I trigger the action event for a member group, the Medical Handbook process errors out. The system returns the following message: ERR62302 – template requires an ENROLL_PRO_METHOD, and none was found. Per Yammanuru, Vijaya B, This is working as designed. Hence closing the defect
A20: 20 | B20: DE1312323 | C20: Nice Rel 3 - CaLPERS - Member Install Failing with OBM 4/27/2026 | D20: Jawahar Soni | E20: Closed | F20: Nice 3 CaLPERS Testing | G20: The Member Install process is failing for OBM. On Friday, April 24, the Enhance file did not complete successfully, and as of today, April 27, the Publish file is also failing.
A21: 21 | B21: DE1317095 | C21: Cirrus (Alpha) – Spring Transaction Rollback Exception/ DE1317119 - Groot to track this issue | D21: Jawahar Soni | E21: In Progress | F21: Nice 3 CaLPERS Testing | G21: The error occurs while updating the Customer Attributes
A22: 22 | B22: DE1287866 | C22: INC48998946:-Comma are appearing in PCP field in Optum Rx Nxt Gen Application | D22: Jawahar Soni | E22: Closed | F22: Nice 2 CarveOut | G22: This defect is assigned to Naman Sharma. It is a global issue and is not specific to any project. Development is currently in progress.
A23: 23 | B23: DE1339524 | C23: RX Carve Out Benefit Bundles need to be updated | D23: Sandia Mitchell | E23: Closed | F23: Nice 2 CarveOut
A24: 24 | B24: DE1339546 | C24: RX Carve Out Agate ID needs to be updated | D24: Sandia Mitchell | E24: Closed | F24: Nice 2 CarveOut
A25: 25 | B25: DE1339551 | C25: Accum Transaction issues in OIL layer | D25: Sandia Mitchell | E25: Closed | F25: Nice 2 CarveOut
A26: 26 | B26: DE1339550 | C26: NICE CA carveout pharmacy not flowing to downstream partners in production | D26: Sandia Mitchell | E26: Closed | F26: Nice 2 CarveOut
A27: 27 | B27: PGA4629 | C27: PGA for DE1339550: NICE CA carveout pharmacy not flowing to downstream partners in production | E27: In Progress | F27: Nice 2 CarveOut

Sheet Project Details
